Workbook

Sheet DATA_SURAT_PELANTIKAN
A1: Bil | B1: Tahun | C1: Tarikh | D1: Kepada (pengerusi) | E1: Penolong Pengerusi | F1: panel 1 | G1: panel 2 | H1: alamat / Fakulti | I1: Pengerusi/Panel (Fakulti lain) | J1: panel (Fakulti lain) | K1: Fakulti | L1: Tajuk (SEMULA) | M1: Tajuk | N1: Tajuk (re-Proposal Defense) | O1: Panggilan hormat | P1: Panggilan hormat_2 | Q1: Punca kuasa | R1: Isi surat 1 | S1: isi surat 2 | T1: Program | U1: Bidang | V1: Nama Pelajar | W1: No. Matrik | X1: Tajuk Proposal | Y1: Tarikh | Z1: Masa | AA1: Tempat | AB1: sk 1 | AC1: sk 2 | AD1: sk 3 | AE1: Nota | AF1: Rujukan Surat Pelantikan | AG1: Tarikh Surat | AH1: Tajuk Penterjemah | AI1: Kelulusan Khidmat Penterjemah (We are glad/ We regret) | AJ1: Kelulusan (SUCCESSFUL/ UNSUCCESSFUL) | AK1: Kategori Penterjemahan
A2: 1 | C2: MEI | D2: Dr. Shah Iskandar Fahmie bin Ramlee | E2: Dr. Nur Syakirah binti Ahmad | F2: Prof. Dr. Raja Suzana binti Raja Kasim | G2: Dr. Norzalizah binti Bahari | H2: Fakulti Keusahawanan dan Perniagaan | L2: SEMULA | N2: re-PROPOSAL DEFENSE | O2: YBhg. Prof./Dr. | P2: YBhg. Prof./Dr. | Q2: Mesyuarat Jawatankuasa Pascasiswazah Bil. 4/2024 (kali ke-45) | R2: Semula | S2: re-Proposal Defense | T2: Doktor Falsafah | U2: Keusahawanan | V2: Abu Bakar bin Busmah | W2: A21E0127P | X2: Kesan Kompetensi Keusahawanan Terhadap Prestasi Koperasi Sekolah Melalui Tingkah Laku Kepimpinan Transformasi Anggota Lembaga Koperasi Sekolah di Malaysia | Y2: 24 Jun 2024 (Isnin) | Z2: 11.00 pagi | AA2: Platform Zoom (pautan akan dimaklumkan kemudian) | AB2: 1) Prof. Dr. Roselina binti Ahmad Saufi (Penyelia Utama) | AC2: 2) Dr. Noor Raihani binti Zainol (Penyelia Bersama)
A3: 2 | C3: MEI | D3: Dr. Syarizal bin Abdul Rahim | E3: Dr. Siti Som binti Husin | F3: Prof. Madya Dr. Dzulkifli bin Mukhtar | G3: Prof. Madya Dr. Mohd Nazri bin Zakaria | H3: Fakulti Keusahawanan dan Perniagaan | L3: SEMULA | N3: re-PROPOSAL DEFENSE | O3: YBrs. Prof. Madya/Dr. | P3: YBrs. Prof. Madya/Dr. | Q3: Mesyuarat Jawatankuasa Pascasiswazah Bil. 4/2024 (kali ke-45) | R3: Semula | S3: re-Proposal Defence | T3: Doktor Falsafah | U3: Pengurusan | V3: Chen Li | W3: A20E0214F | X3: The Effectiveness of Performance Management Module (PMM) on Nurse Performance with Moderating Effect of Willingness to Use HMIS Among Nurses in Hunan Public Hospitals | Y3: 28 Mei 2024 (selasa) | Z3: 10.30 pagi | AA3: Platform Zoom (pautan akan dimaklumkan kemudian) | AB3: 1) Prof. Madya Dr. Muhamad Saufi bin Che Rusuli (Penyelia Utama) | AC3: 2) Prof. Madya Dr. Noorshella binti Che Nawi (Jawatankuasa Penyeliaan) | AD3: 3) Dr. wan Mohd Nazdrol bin Wan Mohd Nasir (Jawatankuasa Penyeliaan)
A4: 3 | C4: MEI | D4: Prof. Madya. Dr. Mohd Zulkifli bin Muhammad | E4: Dr. Siti Salwani binti Abdullah | F4: Dr. Siti Fariha binti Muhamad | G4: Dr. Muhammad Jaffri bin Mohd Nasir | H4: Fakulti Keusahawanan dan Perniagaan | N4: PROPOSAL DEFENSE | O4: YBrs. Prof. Madya/Dr. | P4: YBrs. Prof. Madya/Dr. | Q4: Mesyuarat Jawatankuasa Pascasiswazah Bil. 4/2024 (kali ke-45) | S4: Proposal Defense | T4: Sarjana | U4: Kewangan | V4: Nursyahiyatul Anis binti Othman | W4: A23D053F | X4: Asseccing A Comprehensive Cost Analysis on Meliodosis in Northern Malaysia | Y4: 12 Jun 2024 (Rabu) | Z4: 2.30 petang | AA4: Platform Zoom (pautan akan dimaklumkan kemudian) | AB4: 1) Dr. Mardhiah binti Kamaruddin (Penyelia Utama) | AC4: 2) Prof. Madya Dr. Hazriah binti Hasan (Penyelia Bersama)
A5: 4 | C5: MEI | D5: Dr. Syarizal bin Abdul Rahim | E5: Dr. Norhafifah binti Samsudin | F5: Prof. Madya Dr. Wan Farha binti Wan Zulkiffli | G5: Dr. Mohd Ikhwan bin Aziz | H5: Fakulti Keusahawanan dan Perniagaan | N5: PROPOSAL DEFENSE | O5: YBrs. Prof. Madya/Dr. | P5: YBrs. Prof. Madya/Dr. | Q5: Mesyuarat Jawatankuasa Pascasiswazah Bil. 4/2024 (kali ke-45) | S5: Proposal Defense | T5: Doktor Falsafah | U5: Pengurusan | V5: Chen Zaidie | W5: A20E054F | X5: Exploring the Enduring Influence of Perceived of External Control and Computer Playfulness towards Behavioral Intention on User Adoption of Banking Mobile Applications in Hangzhou City Commercial Bank: The Mediating effect of Perceived Ease of Use | Y5: 27 Mei 2024 (Isnin) | Z5: 9.30 pagi | AA5: Platform Zoom (pautan akan dimaklumkan kemudian) | AB5: 1) Dr. Fatihah binti Mohd (Penyelia Utama) | AC5: 2) Dr. Nur Ain Ayunni binti Sabri (Penyelia Bersama)
A6: 5 | C6: MEI | D6: Prof. Madya Dr. Dzulkifli bin Mukhtar | E6: Dr. Siti Rohana binti Mohamad | F6: Dr. Zaminor binti Zamzamir @ Zamzamin | G6: Dr. Ahmad Ridhuwan bin Abdullah | H6: Fakulti Keusahawanan dan Perniagaan | N6: PROPOSAL DEFENSE | O6: YBrs. Prof. Madya/Dr. | P6: YBrs. Prof. Madya/Dr. | Q6: Mesyuarat Jawatankuasa Pascasiswazah Bil. 4/2024 (kali ke-45) | S6: Proposal Defense | T6: Doktor Falsafah | U6: Kewangan | V6: Ma Jianmei | W6: A21E013F | X6: The Impact of Digital Inclusive Finance on Financing Constraints of Small and Medium Sized Enterprises in China. | Y6: 29 Mei 2024 (Rabu) | Z6: 9.30 pagi | AA6: Platform Zoom (pautan akan dimaklumkan kemudian) | AB6: 1) Dr. Noormariana binti Mohd Din (Penyelia Utama)
A7: 6 | C7: JUN | D7: Prof. Madya Dr. Dzulkifli bin Mukhtar | E7: Dr. Nur Fadiah binti Mohd Zawawi | F7: Prof. Dr. Mohd Nor Hakimin bin Yusoff | G7: Prof. Dr. Mohd Rafi bin Yaacob | H7: Fakulti Keusahawanan dan Perniagaan | N7: PROPOSAL DEFENSE | O7: YBhg. Prof. | P7: YBhg. Prof. | Q7: Mesyuarat Jawatankuasa Pascasiswazah Bil. 4/2024 (kali ke-45) | S7: Proposal Defense | T7: Doktor Falsafah | U7: Perakaunan | V7: Syukry Hadi | W7: A19E0039F | X7: Determinants of Job Performance Among Financial Employees in Indonesia Private Hospital : The Role of Intrapreneurship as Mediator and Psychological Ownership as Moderator | Y7: 8 Julai 2024 (Isnin) | Z7: 10.00 pagi | AA7: Platform Zoom (pautan akan dimaklumkan kemudian) | AB7: 1) Prof. Dato’ Dr. Razli bin Che Razak (Penyelia Utama)
A8: 7 | C8: MEI | D8: Prof. Dr. Balakrishnan a/l Parasuraman | E8: Dr. Norzalizah binti Bahari | F8: Prof. Dr. Mohd Nor Hakimin bin Yusoff | G8: Prof. Madya Dr. Mohd Nazri bin Zakaria | H8: Fakulti Keusahawanan dan Perniagaan | N8: PROPOSAL DEFENSE | O8: YBhg. Prof. | P8: YBhg. Prof. | Q8: Mesyuarat Jawatankuasa Pascasiswazah Bil. 4/2024 (kali ke-45) | S8: Proposal Defense | T8: Doktor Falsafah | U8: Pengurusan | V8: Muhammad Fikry Hadi | W8: A19E0023F | X8: Pengaruh Kepimpinan Transformasi dan Komitmen Organisasi Terhadap Prestasi Kerja Pensyarah Universiti Muhammadiyah di Indonesia : Kesan Pengantara Kepuasan Kerja dan Penyederhanaan Kepimpinan Rohani | Y8: 6 Jun 2024 (Khamis) | Z8: 9.30 pagi | AA8: Platform Zoom (pautan akan dimaklumkan kemudian) | AB8: 1) Prof. Dato’ Dr. Razli bin Che Razak (Penyelia Utama) | AC8: 2) Dr. Nurul Hafizah binti Mohd Yasin (Penyelia Bersama)
A9: 8 | C9: MEI | D9: Dr. Nur Syafiqah binti A. Samad | E9: Pn. Nik Noorhazila binti Nik Mud | F9: Dr. Nor Asma binti Ahmad | G9: Dr. Zaminor binti Zamzamir @ Zamzamin | H9: Fakulti Keusahawanan dan Perniagaan | N9: PRA PEPERIKSAAN LISAN (PRE VIVA) | O9: YBrs. Dr./Puan | P9: YBrs. Dr./Puan | Q9: Mesyuarat Jawatankuasa Pascasiswazah Bil. 4/2024 (kali ke-45) | S9: Pra Peperiksaan Lisan (Pre Viva) | T9: Doktor Falsafah | U9: Kewangan | V9: Nurza binti Mohamed Yusoff | W9: A18E025F | X9: The Nexus of Financial Development, Employment, and Economic Growth in Developing Countries: The Role of Minimum Wage | Y9: 9 Jun 2024 (Ahad) | Z9: 2.30 petang | AA9: Platform Zoom (pautan akan dimaklumkan kemudian) | AB9: 1) Dr Nurnaddia binti Nordin (Penyelia Utama) | AC9: 2) Dr. Nurhaiza binti Nordin (Penyelia Bersama)
A10: 9 | C10: MEI | D10: Dr. Azira Hanani binti Berahim @ Ab Rahman | E10: Pn. Nik Madeeha binti Nik Mohd Munir | F10: Dr. Nor Asma binti Ahmad | G10: Dr. Zaminor binti Zamzamir @ Zamzamin | H10: Fakulti Keusahawanan dan Perniagaan | N10: PRA PEPERIKSAAN LISAN (PRE VIVA) | O10: YBrs. Dr./Puan | P10: YBrs. Dr./Puan | Q10: Mesyuarat Jawatankuasa Pascasiswazah Bil. 4/2024 (kali ke-45) | S10: Pra Peperiksaan Lisan (Pre Viva) | T10: Doktor Falsafah | U10: Kewangan | V10: Han Yue | W10: A20E0110F | X10: Evaluation of Macroeconomic Models for Financial Stability Analysis: A Case Study of Financial Market in China | Y10: 12 Jun 2024 (Rabu) | Z10: 11.00 pagi | AA10: Platform Zoom (pautan akan dimaklumkan kemudian) | AB10: 1) Dr Nurnaddia binti Nordin (Penyelia Utama) | AC10: 2) Dr. Nurhaiza binti Nordin (Penyelia Bersama)
A11: 10 | C11: MEI | D11: Prof. Madya. Dr. Mohd Zulkifli bin Muhammad | E11: Pn. Aimi Nadia binti Ibrahim @ Zakaria | F11: Prof. Madya Dr. Muhamad Saufi bin Che Rusuli | G11: Prof. Madya Dr. Noorshella binti Che Nawi | H11: Fakulti Keusahawanan dan Perniagaan | N11: PRA PEPERIKSAAN LISAN (PRE VIVA) | O11: YBrs. Prof. Madya/puan | P11: YBrs. Prof. Madya/puan | Q11: Mesyuarat Jawatankuasa Pascasiswazah Bil. 4/2024 (kali ke-45) | S11: Pra Peperiksaan Lisan (Pre Viva) | T11: Doktor Falsafah | U11: Peruncitan | V11: Haidong Zhang | W11: A20E002F | X11: The Relationship Between The Big Data Analysis Capability, External Knowledge Search and Omni-Channel Marketing on Firm Performance in China | Y11: 11 Jun 2024 (Selasa) | Z11: 11.00 pagi | AA11: Platform Zoom (pautan akan dimaklumkan kemudian) | AB11: 1) Prof. Madya Ts. Dr. Zailani bin Abdullah (Penyelia Utama)
A12: 11 | C12: MEI | D12: Prof. Madya Dr. Mohd Nazri bin Zakaria | E12: Dr. Syamsuriana binti Sidek | F12: Prof. Dr. Mohd Rafi bin Yaacob | G12: Prof. Madya Ts. Dr. Zuraimi bin Abdul Aziz | H12: Fakulti Keusahawanan dan Perniagaan | L12: SESI PENILAIAN SEMULA | N12: PRA PEPERIKSAAN LISAN (re-PRE VIVA) | O12: YBhg. Prof./Prof. Madya/Dr. | P12: YBhg. Prof./Prof. Madya/Dr. | Q12: Mesyuarat Jawatankuasa Pascasiswazah Bil. 4/2024 (kali ke-45) | R12: Sesi Penilaian Semula | S12: Pra Peperiksaan Lisan (re-Pre Viva) | T12: Doktor Falsafah | U12: Keusahawanan | V12: Fadhilahanim Aryani binti Abdullah | W12: C14E008P | X12: Innovation Competency and Innovation Capability on SME’s Innovation Performance in Malaysia Health Tourism Industry: Moderating Effects of Digital Technology Diffusion | Y12: 10 Julai 2024 (Rabu) | Z12: 9.30 pagi | AA12: Platform Zoom (pautan akan dimaklumkan kemudian) | AB12: 1) Prof. Dato' Dr. Nik Maheran binti Nik Muhammad (Penyelia Utama)
A13: 12 | C13: MEI | D13: Prof. Madya Dr. Mohd Nazri bin Zakaria | E13: Dr. Syamsuriana binti Sidek | F13: Prof. Dr. Raja Suzana binti Raja Kasim | G13: Dr. Nor Hafiza binti Othman | H13: Fakulti Keusahawanan dan Perniagaan | N13: PRA PEPERIKSAAN LISAN (PRE VIVA) | O13: YBhg. Prof./Prof. Madya/Dr. | P13: YBhg. Prof./Prof. Madya/Dr. | S13: Pra Peperiksaan Lisan (Pre Viva) | T13: Doktor Falsafah | U13: Keusahawanan | V13: Reni Mutiarani Saraswati | W13: A20E0179F | X13: Social Entrepreneurial Orientation on Sustainability Performance Among social Business Organizations in Indonesia | Y13: 5 Jun 2024 (Rabu) | Z13: 11.00 pagi | AA13: Platform Zoom (pautan akan dimaklumkan kemudian) | AB13: 1) Dr. Noor Raihani binti Zainol (Penyelia Utama) | AC13: 2) Dr. Suhaila binti Abdul Kadir (Penyelia Bersama)
A14: 13 | C14: JUN | D14: Prof. Madya Dr. Noorul Azwin binti Md Nasir | E14: Dr. Nor Asma binti Ahmad | F14: Dr. Tahirah binti Abdullah | G14: Dr. Mohd Rushdan bin Yasoa’ | H14: Fakulti Keusahawanan dan Perniagaan | N14: PENILAIAN CADANGAN PENYELIDIKAN (PROPOSAL DEFENSE) | O14: YBrs. Prof. Madya/Dr. | P14: YBrs. Prof. Madya/Dr. | Q14: Mesyuarat Jawatankuasa Pascasiswazah Bil. 5/2024 (kali ke-46) | S14: Penilaian Cadangan Penyelidikan (Proposal Defense) | T14: Sarjana | U14: Pengurusan | V14: Huang Jiayi | W14: A22D106F | X14: Green Accounting by SME in China: An Application of Theory of Planned and Behaviour | Y14: 12 Ogos 2024 (Isnin) | Z14: 10.00 pagi | AA14: Platform Zoom (pautan akan dimaklumkan kemudian) | AB14: 1) Dr. Siti Afiqah binti Zainuddin (Penyelia Utama) | AE14: Pengerusi - Prof. Madya Dr. Azwan bin Abdullah (Tukar) Panel 1 - PM. Dr. Nazri bin Zakaria (Tukar)
A15: 14 | C15: JUN | D15: Dr. Kasmaruddin bin Che Hussin | E15: En. Mohamed Ariff bin Abdul Rahman | F15: Prof. Dr. Mohd Rafi bin Yaacob | G15: Dr. Tahirah binti Abdullah | H15: Fakulti Keusahawanan dan Perniagaan | N15: PENILAIAN CADANGAN PENYELIDIKAN (PROPOSAL DEFENSE) | O15: YBhg. Prof./Prof. Madya/Dr. | P15: YBhg. Prof./Prof. Madya/Dr. | Q15: Mesyuarat Jawatankuasa Pascasiswazah Bil. 5/2024 (kali ke-46) | S15: Penilaian Cadangan Penyelidikan (Proposal Defense) | T15: Doktor Falsafah | U15: Perakaunan | V15: Wu Shuangshuang | W15: A21E054F | X15: Study on the Effect of Preferential Tax Policies on Science and Technology Capital | Y15: 14 Julai 2024 (Ahad) | Z15: 10.00 pagi | AA15: Platform Zoom (pautan akan dimaklumkan kemudian) | AB15: 1) Prof. Dr. Mohd Nor Hakimin bin Yusof (Penyelia Utama)
A16: 15 | C16: JUN | D16: Dr. Suhaila binti Abdul Kadir | E16: Dr. Norzalizah binti Bahari | F16: Prof. Madya Dr. Dzulkifli bin Mukhtar | G16: Dr. Nor Hafiza binti Othman | H16: Fakulti Keusahawanan dan Perniagaan | N16: PRA PEPERIKSAAN LISAN (PRE VIVA) | O16: YBrs. Prof. Madya/Dr. | P16: YBrs. Prof. Madya/Dr. | Q16: Mesyuarat Jawatankuasa Pascasiswazah Bil. 5/2024 (kali ke-46) | S16: Pra Peperiksaan Lisan (Pre Viva) | T16: Doktor Falsafah | U16: Pengurusan | V16: Nor Shuhada binti Ahmad Shaupi | W16: A14E010F | X16: Fenomena Pengalaman Peniaga Golongan B40 dalam Persekitaran Mencabar-Pendemik Covid-19: Pendekatan Abduktif Logik | Y16: 16 Julai 2024 (Selasa) | Z16: 10.00 pagi | AA16: Platform Zoom (pautan akan dimaklumkan kemudian) | AB16: 1) Prof. Madya Dr. Anis Amira binti Ab Rahman (Penyelia Utama) | AC16: 2) Prof. Dr. Roslina binti Ahmad Saufi (Penyelia Bersama)
A17: 16 | C17: JUN | D17: Dr. Amira binti Jamil | E17: En. Zul Karami bin Che Musa | F17: Prof. Dr. Mohd Rafi bin Yaacob | G17: Dr. Mohd Rushdan bin Yasoa’ | H17: Fakulti Keusahawanan dan Perniagaan | N17: PENILAIAN CADANGAN PENYELIDIKAN (PROPOSAL DEFENSE) | O17: YBhg. Prof./Prof. Madya/Dr. | P17: YBhg. Prof./Prof. Madya/Dr. | Q17: Mesyuarat Jawatankuasa Pascasiswazah Bil. 5/2024 (kali ke-46) | S17: Penilaian Cadangan Penyelidikan (Proposal Defense) | T17: Doktor Falsafah | U17: Perakaunan | V17: Tippavan Rattanaprom | W17: A19E039F | X17: Factor That Influences the Accounting Practice Among SMEs: A Study on Southern Thai SMEs | Y17: 22 Julai 2024 (Isnin) | Z17: 10.00 pagi | AA17: Platform Zoom (pautan akan dimaklumkan kemudian) | AB17: 1) Prof. Dr. Mohd Nor Hakimin bin Yusof (Penyelia Utama) | AC17: 2) Prof. Madya Dr. Noorul Azwin binti Md Nasir (Penyelia Bersama)
A18: 17 | C18: JUN | D18: Dr. Azira Hanani binti Berahim @ Ab Rahman | E18: En. Zul Karami bin Che Musa | F18: Prof. Madya Dr. Dzulkifli bin Mukhtar | G18: Dr. Siti Fariha binti Muhamad | H18: Fakulti Keusahawanan dan Perniagaan | N18: PRA PEPERIKSAAN LISAN (PRE VIVA) | O18: YBrs. Prof. Madya/Dr. | P18: YBrs. Prof. Madya/Dr. | Q18: Mesyuarat Jawatankuasa Pascasiswazah Bil. 5/2024 (kali ke-46) | S18: Pra Peperiksaan Lisan (Pre Viva Voce) | T18: Doktor Falsafah | U18: Pengurusan | V18: Jia bin | W18: A22E011F | X18: The Effect of Principal-Agent Attributes and Firm Size on Budgetary Slack: Evidence from Manufacturing Listed Firms in China | Y18: 21 Julai 2024 (Ahad) | Z18: 10.00 pagi | AA18: Platform Zoom (pautan akan dimaklumkan kemudian) | AB18: 1) Prof. Madya Dr. Noorul Azwin binti Md Nasir (Penyelia Utama) | AC18: 2) Dr. Zaminor binti Zamzamir @ Zamzamin (Penyelia Bersama) | AD18: 3) Dr. Amira binti Jamil (Penyelia Bersama)
A19: 18 | C19: JUN | D19: Dr. Ahmad Ridhuwan bin Abdullah | E19: Dr. Nur Syakirah binti Ahmad | F19: Dr. Nik Syuhailah binti Nik Hussin | G19: Dr. Norhafifah binti Samsudin | H19: Fakulti Keusahawanan dan Perniagaan | N19: PRA PEPERIKSAAN LISAN (PRE VIVA) | O19: YBhg. Prof./Dr. | P19: YBhg. Prof./Dr. | Q19: Mesyuarat Jawatankuasa Pascasiswazah Bil. 5/2024 (kali ke-46) | S19: Pra Peperiksaan Lisan (Pre Viva Voce) | T19: Doktor Falsafah | U19: Pemasaran | V19: Siti Hanifa Sandri | W19: A19E0029F | X19: Brand Experience and Customer Relationship Marketing Towards Customer Based Brand Equity: Mediator Role of Word of Mouth in Budget Hotels | Y19: 14 Julai 2024 (Ahad) | Z19: 10.00 pagi | AA19: Platform Zoom (pautan akan dimaklumkan kemudian) | AB19: 1) Prof. Madya Dr. Noor Hasmini Hj Abd Ghani (Penyelia Utama)
A20: 19 | C20: JUN | D20: Dr. Rikinorhakis bin Ridzwan | E20: Dr. Norfazlirda binti Hairani | F20: Prof. Madya Dr. Wan Farha binti Wan Zulkiffli | G20: Dr. Nur Syakirah binti Ahmad | H20: Fakulti Keusahawanan dan Perniagaan | N20: PENILAIAN CADANGAN PENYELIDIKAN (PROPOSAL DEFENSE) | O20: YBrs. Prof. Madya/Dr. | P20: YBrs. Prof. Madya/Dr. | Q20: Mesyuarat Jawatankuasa Pascasiswazah Bil. 5/2024 (kali ke-46) | S20: Penilaian Cadangan Penyelidikan (Proposal Defense) | T20: Sarjana | U20: Pemasaran | V20: Amira Nur Syafiah binti Mohammad | W20: A21D053F | X20: Service Quality, Customer Satisfaction and Continuous Intention For Training Provider in East Coast Region | Y20: 15 Julai 2024 (Isnin) | Z20: 10.00 pagi | AA20: Platform Zoom (pautan akan dimaklumkan kemudian) | AB20: 1) Dr. Nik Syuhailah binti Hussin (Penyelia Utama) | AC20: 2) Puan Nadia Hanum binti Amiruddin (Penyelia Bersama)
A21: 20 | C21: JUN | D21: Dr. Siti Rohana binti Mohamad | E21: Dr. Muhammad Firdaus bin Zakaria | F21: Prof. Madya Dr. Hazriah binti Hasan | G21: Dr. Mohd Afifie bin Mohd Alwi | H21: Fakulti Keusahawanan dan Perniagaan | N21: PENILAIAN CADANGAN PENYELIDIKAN (PROPOSAL DEFENSE) | O21: YBrs. Prof. Madya/Dr. | P21: YBrs. Prof. Madya/Dr. | Q21: Mesyuarat Jawatankuasa Pascasiswazah Bil. 5/2024 (kali ke-46) | S21: Penilaian Cadangan Penyelidikan (Proposal Defense) | T21: Doktor Falsafah | U21: Perbankan dan Kewangan Islam | V21: Muhammad Lisman | W21: A19E0041F | X21: Indonesian Sharia Banking Transformation Model In The Digital Era | Y21: 24 Julai 2024 (Rabu) | Z21: 10.00 pagi | AA21: Platform Zoom (pautan akan dimaklumkan kemudian) | AB21: 1) Prof. Madya Dr. Mohd Zulkifli bin Muhammad (Penyelia Utama) | AC21: 2) Dr. Muhammad Zulfaris bin Mohd Salleh (Penyelia Bersama)
A22: 21 | C22: JUN | D22: Prof. Madya Dr. Azwan bin Abdullah | E22: Dr. Mohd Ikhwan bin Aziz | F22: Prof. Dr. Mohd Rafi bin Yaacob | G22: Prof. Madya Dr. Dzulkifli bin Mukhtar | H22: Fakulti Keusahawanan dan Perniagaan | N22: PENILAIAN CADANGAN PENYELIDIKAN (PROPOSAL DEFENSE) | O22: YBhg. Prof./Prof. Madya/Dr. | P22: YBhg. Prof./Prof. Madya/Dr. | Q22: Mesyuarat Jawatankuasa Pascasiswazah Bil. 5/2024 (kali ke-46) | S22: Penilaian Cadangan Penyelidikan (Proposal Defense) | T22: Doktor Falsafah | U22: Pengurusan | V22: Mohammad Firdaus bin Nizam | W22: A22E048F | X22: Leadership Style in Performance of Waqf at University Putra Malaysia (UPM) and Fatoni University (FU), Thailand : Exploratory Qualitative Case Study | Y22: 25 Julai 2024 (Khamis) | Z22: 10.00 pagi | AA22: Platform Zoom (pautan akan dimaklumkan kemudian) | AB22: 1) Prof. Dr. Balakrishnan a/l Parasuraman (Penyelia Utama) | AC22: 2) Prof. Madya Dr. Hazriah binti Hasan (Penyelia Bersama)
A23: 22 | C23: JULAI | D23: Dr. Syamsuriana binti Sidek | E23: Dr. Norhafifah binti Samsudin | F23: Prof. Madya Dr. Mohd Nazri bin Zakaria | G23: Dr. Hasannuddiin bin Hassan | H23: Fakulti Keusahawanan dan Perniagaan | N23: PRA PEPERIKSAAN LISAN (PRE VIVA VOCE) | O23: YBrs. Prof. Madya/Dr. | P23: YBrs. Prof. Madya/Dr. | Q23: Mesyuarat Jawatankuasa Pascasiswazah Bil. 6/2024 (kali ke-47) | S23: Pra Peperiksaan Lisan (Pre Viva Voce) | T23: Doktor Falsafah | U23: Keusahawanan | V23: Kuwata Muhammad Goni | W23: A20E0238F | X23: Green Human Resource Management, Green Innovation, and Environmental Performance of Hotel in Kano Nigeria: Moderating Role of Green Transformational Leadership | Y23: 4 Ogos 2024 (Ahad) | Z23: 10.00 pagi | AA23: Platform Zoom (pautan akan dimaklumkan kemudian) | AB23: 1) Dr. Shah Iskandar Fahmie bin Ramlee (Penyelia Utama) | AC23: 2) Dr. Tahirah binti Abdullah (Penyelia Bersama)
A24: 23 | C24: JULAI | D24: Dr. Mohd Ikhwan bin Aziz | E24: En. Ahmad Syakir bin Junoh @ Ismail | F24: Prof. Dr. Mohd Nor Hakimin bin Yusoff | G24: Dr. Nor Hafiza binti Othman | H24: Fakulti Keusahawanan dan Perniagaan | N24: PRA PEPERIKSAAN LISAN (PRE VIVA VOCE) | O24: YBhg. Prof. Dr./Dr. | P24: YBhg. Prof. Dr./Dr. | Q24: Mesyuarat Jawatankuasa Pascasiswazah Bil. 6/2024 (kali ke-47) | S24: Pra Peperiksaan Lisan (Pre Viva Voce) | T24: Doktor Falsafah | U24: Keusahawanan | V24: Rika Verawati | W24: A20E074F | X24: Minat Mahasiswa Dalam Bidang Pendidikan Keusahawanan Di Universiti PGRI Sumatera Barat | Y24: 6 Ogos 2024 (Selasa) | Z24: 10.00 pagi | AA24: Platform Zoom (pautan akan dimaklumkan kemudian) | AB24: 1) Prof. Dr. Mohd Rafi bin Yaacob (Penyelia Utama)
A25: 24 | C25: JULAI | D25: Dr. Ahmad Ridhuwan bin Abdullah | E25: Dr. Siti Fariha binti Muhamad | F25: Prof. Dr. Mohd Rafi bin Yaacob | G25: Prof. Madya Dr. Noorul Azwin binti Md Nasir | H25: Fakulti Keusahawanan dan Perniagaan | N25: PRA PEPERIKSAAN LISAN (PRE VIVA VOCE) | O25: YBhg. Prof. Dr./Prof. Madya/Dr. | P25: YBhg. Prof. Dr./Prof. Madya/Dr. | Q25: Mesyuarat Jawatankuasa Pascasiswazah Bil. 6/2024 (kali ke-47) | S25: Pra Peperiksaan Lisan (Pre Viva Voce) | T25: Doktor Falsafah | U25: Perakaunan | V25: Muhammad Ahyaruddin | W25: A19E0019F | X25: Institutional Isomorphism, Accountability and Local Government Performance in Riau Public Governance: Autonomy and Management Commitment as Moderating Variable | Y25: 7 Ogos 2024 (Rabu) | Z25: 10.00 pagi | AA25: Platform Zoom (pautan akan dimaklumkan kemudian) | AB25: 1) Prof. Dr. Mohd Nor Hakimin bin Yusoff (Penyelia Utama) | AC25: 2) Dr. Siti Afiqah binti Zainuddin (Penyelia Bersama) | AE25: Pengerusi - Prof. Madya Dr. Wan Farha binti Wan Zulkiffli (Tukar)
A26: 25 | C26: OGOS | D26: Dr. Syarizal bin Abdul Rahim | E26: Dr. Muhammad Zulfaris bin Mohd Salleh | F26: Dr. Ahmad Ridhuwan bin Abdullah | G26: Dr. Noor Raihani binti Zainol | H26: Fakulti Keusahawanan dan Perniagaan | N26: PENILAIAN SEMULA CADANGAN PENYELIDIKAN (re-PROPOSAL DEFENSE) | O26: YBrs. Dr. | P26: YBrs. Dr. | S26: Penilaian Semula Cadangan Penyelidikan (re-Proposal Defense) | T26: Doktor Falsafah | U26: Keusahawanan | V26: Sofia Samaalee | W26: A19E040F | X26: The Influence of Investing knowledge and behavioral factors towards the performance of individual investors in the trading shares of companies listed at The Stock Exchange, Thailand using investment decision making as a mediator | Y26: 5 September 2024 (Khamis) | Z26: 10.00 pagi | AA26: Platform Zoom (pautan akan dimaklumkan kemudian) | AB26: 1) Dr. Nur Ain Ayuni binti Sabri (Penyelia Utama) | AC26: 2) Dr. Azira Hanani binti Berahim @ Ab Rahman (Penyelia Bersama) | AD26: 3) Prof. Madya Dr. Dzulkifli bin Mukhtar (Penyelia Bersama) | AE26: Pen. Pengerusi - Dr. Muhammad Zulfaris bin Mohd Salleh (Tukar)
A27: 26 | C27: OGOS | D27: Dr. Hanieh Alipour Bazkiaei | E27: Dr. Nur Syafiqah binti A. Samad | F27: Dr. Noor Ullah Khan | G27: Prof. Madya Dr. Ng Siew Foen | H27: Fakulti Keusahawanan dan Perniagaan | N27: PENILAIAN CADANGAN PENYELIDIKAN (PROPOSAL DEFENSE) | O27: YBrs. Prof. Madya/Dr. | P27: YBrs. Prof. Madya/Dr. | Q27: Mesyuarat Jawatankuasa Pascasiswazah Bil. 7/2024 (kali ke-48) | S27: Penilaian Cadangan Penyelidikan (Proposal Defense) | T27: Sarjana Keusahawanan | U27: Pengurusan Sumber Manusia | V27: Thiiruchelvi a/p Gunasagaran | W27: A20D077P | X27: English as a Second Language (ESL) Teachers Preparedness Towards Students Achievements | Y27: 19 Ogos 2024 (Isnin) | Z27: 10.00 pagi | AA27: Platform Zoom (pautan akan dimaklumkan kemudian) | AB27: 1) Dr. P. Yukthamarani a/p Permarupan
A28: 27 | C28: OGOS | D28: Dr. Norfazlirda binti Hairani | E28: Pn. Nurul Hasliana binti Hamsani | F28: Dr. Nik Syuhailah binti Nik Hussin | G28: Dr. Nur Syakirah binti Ahmad | H28: Fakulti Keusahawanan dan Perniagaan | N28: PENILAIAN CADANGAN PENYELIDIKAN (PROPOSAL DEFENSE) | O28: YBrs. Dr. | P28: YBrs. Dr. | Q28: Mesyuarat Jawatankuasa Pascasiswazah Bil. 7/2024 (kali ke-48) | S28: Penilaian Cadangan Penyelidikan (Proposal Defense) | T28: Doktor Falsafah | U28: Pemasaran | V28: Shen Ke | W28: A21E049F | X28: The Impact of eWOM Characteristics on Intention to Travel to Destination Among Generation Z in China: Mediating by Attitude Towards Information Adoption | Y28: 22 September 2024 (Ahad) | Z28: 10.00 pagi | AA28: Platform Zoom (pautan akan dimaklumkan kemudian) | AB28: 1) Prof. Madya Dr. Wan Farha binti Wan Zulkiffli | AE28: Pengerusi - Dr. Nur Syakirah binti Ahmad (tukar) Panel 1 - Prof. Dr. Mohammad bin ismail (tukar)
A29: 28 | C29: OGOS | D29: Prof. Madya. Dr. Mohd Zulkifli bin Muhammad | E29: Dr. Amira binti Jamil | F29: Prof. Madya Dr. Anis Amira binti Ab Rahman | G29: Dr. Siti Salwani binti Abdullah | H29: Fakulti Keusahawanan dan Perniagaan | N29: PENILAIAN CADANGAN PENYELIDIKAN (PROPOSAL DEFENSE) | O29: YBrs. Prof. Madya/Dr. | P29: YBrs. Prof. Madya/Dr. | Q29: Mesyuarat Jawatankuasa Pascasiswazah Bil. 7/2024 (kali ke-48) | S29: Penilaian Cadangan Penyelidikan (Proposal Defense) | T29: Doktor Falsafah | U29: Keusahawanan | V29: Muhammad Umar | W29: A22E115F | X29: An Investigation of Innovation-Driven Enterprises Growth Strategies in the Newly Emerging Economy of Sub-Saharan Africa: A Nigerian Case Study | Y29: 20 Ogos 2024 (Selasa) | Z29: 10.00 pagi | AA29: Platform Zoom (pautan akan dimaklumkan kemudian) | AB29: 1) Prof. Madya Dr. Dzulkifli bin Mukhtar (Penyelia Utama) | AC29: 2) Dr. Mohd Ikhwan bin Aziz (Penyelia Bersama)
A30: 29 | C30: OGOS | D30: Dr. Tahirah binti Abdullah | E30: Dr. Tan Wai Hong | F30: Dr. Mohd Afifie bin Mohd Alwi | G30: Dr. Siti Rohana binti Mohamad | H30: Fakulti Keusahawanan dan Perniagaan | N30: PENILAIAN CADANGAN PENYELIDIKAN (PROPOSAL DEFENSE) | O30: YBrs. Dr. | P30: YBrs. Dr. | Q30: Mesyuarat Jawatankuasa Pascasiswazah Bil. 7/2024 (kali ke-48) | S30: Penilaian Cadangan Penyelidikan (Proposal Defense) | T30: Doktor Falsafah | U30: Kewangan | V30: Song Ziyan | W30: A21E016F | X30: The Effects of Empathy and the Moderating Role of Regulatory Focus on Donors Decision to Support Philanthropic Crowdfunding in China | Y30: 9 September 2024 (Isnin) | Z30: 10.00 pagi | AA30: Platform Zoom (pautan akan dimaklumkan kemudian) | AB30: 1) Dr. Ahmad Ridhuwan bin Abdullah (Penyelia Utama) | AC30: 2) Dr. Siti Salwani binti Abdullah (Penyelia Bersama) | AD30: 3) Dr. Nur Farahiah binti Azmi (Penyelia Bersama) | AE30: Pengerusi - Dr. Amira bintil Jamil (Tukar) Panel 1 - Prof. Madya Dr. Azwan bin Abdullah (tukar)
A31: 30 | C31: OGOS | D31: Dr. Hasannuddiin bin Hassan | F31: Prof. Dr. Balakrishnan a/l Parasuraman | G31: Prof. Dr. Mohd Nor Hakimin bin Yusoff | H31: Fakulti Keusahawanan dan Perniagaan | L31: SEMULA | N31: re-PROPOSAL DEFENSE | O31: YBhg. Prof./Dr. | P31: YBhg. Prof./Dr. | Q31: Mesyuarat Jawatankuasa Pascasiswazah Bil. 7/2024 (kali ke-48) | S31: re-Proposal Defence | T31: Doktor Falsafah | U31: Peruncitan | V31: Wan Ahmad Rizal bin Mohd Yusoff | W31: A19E026F | X31: A Study on Interpersonal Skills Among Selected Cases of Successful Malay Entrepreneurs Wholesale SMGs in Terengganu. | Y31: 25 Ogos 2024 (Ahad) | Z31: 10.00 pagi | AA31: Platform Zoom (pautan akan dimaklumkan kemudian) | AB31: 1) Prof. Dr. Mohd Rafi bin Yaacob (Penyelia Utama)
A32: 31 | C32: OGOS | D32: Dr. Siti Zamanira binti Mat Zaib | E32: Pn. Azizah binti Musa | F32: Prof. Madya Dr. Hazriah binti Hasan | G32: Dr. Aikal Liyani binti Mohd Rasdi | H32: Fakulti Keusahawanan dan Perniagaan | L32: SEMULA | N32: re-PROPOSAL DEFENSE | O32: YBrs. Prof. Madya/Dr. | P32: YBrs. Prof. Madya/Dr. | Q32: Mesyuarat Jawatankuasa Pascasiswazah Bil. 7/2024 (kali ke-48) | S32: re-Proposal Defence | T32: Doktor Falsafah | U32: Perdagangan | V32: Mizan Asnawi | W32: A19E0045F | X32: Examining the Readiness of SMEs in Implementing Halal Tourism in Indonesia: A Study using the Components Theory of Planned Behavior and Halal Tourism Literacy as Moderator | Y32: 25 Ogos 2024 (Ahad) | Z32: 10.00 pagi | AA32: Platform Zoom (pautan akan dimaklumkan kemudian) | AB32: 1) Dr. Siti Salwani binti Abdullah (Penyelia Utama)
A33: 32 | C33: OGOS | D33: Dr. Siti Rohana binti Mohamad | E33: En. Syed Azlan Aljaffree bin Syed Khadzil | F33: Prof. Madya Dr. Azwan bin Abdullah | G33: Dr. Siti Fariha binti Muhamad | H33: Fakulti Keusahawanan dan Perniagaan | L33: SEMULA | N33: re-PROPOSAL DEFENSE | O33: YBrs. Prof. Madya/Dr. | P33: YBrs. Prof. Madya/Dr. | Q33: Mesyuarat Jawatankuasa Pascasiswazah Bil. 7/2024 (kali ke-48) | S33: re-Proposal Defence | T33: Doktor Falsafah | U33: Kewangan | V33: Wen Peicheng | W33: A20E0201F | X33: Moderating Effects of USD Cycle and RMB Exchange Rate on Capital Market Linkage in China | Y33: 26 Ogos 2024 (Isnin) | Z33: 10.00 pagi | AA33: Platform Zoom (pautan akan dimaklumkan kemudian) | AB33: 1) Dr. Nurhaiza binti Nordin (Penyelia Utama) | AC33: 2) Dr Nurnaddia binti Nordin (Penyelia Bersama)
A34: 33 | C34: OGOS | D34: Dr. Tahirah binti Abdullah | F34: Dr. Mohd Rushdan bin Yasoa’ | G34: Dr. Siti Salwani binti Abdullah | H34: Fakulti Keusahawanan dan Perniagaan | N34: PRA PEPERIKSAAN LISAN (PRE VIVA VOCE) | O34: YBrs. Dr. | P34: YBrs. Dr. | S34: Pra Peperiksaan Lisan (Pre Viva Voce) | T34: Doktor Falsafah | U34: Perakaunan | V34: Evi Dwi Kartikasari | W34: A22E105F | X34: The Macro and Micro Organizational Elements and BUMDesa Performance in Indonesia: A Multiple Case Studies Approach | Y34: 5 Ogos 2024 (Isnin) | Z34: 2.30 petang | AA34: Platform Google Meet | AB34: 1) Dr. Siti Afiqah binti Zainuddin (Penyelia Utama) | AC34: 2) Dr. Amira binti Jamil (Penyelia Bersama)
A35: 34 | C35: OGOS | D35: Dr. Nur Syakirah binti Ahmad | E35: Puan Nadia Hanum binti Amiruddin | F35: Dr. Norhafifah binti Samsudin | G35: Dr. Norfazlirda binti Hairani | H35: Fakulti Keusahawanan dan Perniagaan | N35: PRA PEPERIKSAAN LISAN (PRE VIVA VOCE) | O35: YBrs. Dr./Puan | P35: YBrs. Dr./Puan | S35: Pra Peperiksaan Lisan (Pre Viva Voce) | T35: Sarjana Keusahawanan | U35: Pemasaran | V35: Zhuang Haimei | W35: A22D123F | X35: A Study on the Customer Purchase Intention Toward Colorkey Cosmetic Products In China | Y35: 13 Ogos 2024 (Selasa) | Z35: 10.00 pagi | AA35: Platform Zoom (pautan akan dimaklumkan kemudian) | AB35: 1) En. Mohammad Nizamuddin bin Abdul Rahim (Penyelia Utama)
A36: 35 | C36: OGOS | D36: Prof. Madya Dr. Muhammad Ashlyzan bin Razik | E36: Dr. Nur Syafiqah binti A. Samad | F36: Prof. Madya Dr. Noorul Azwin binti Md Nasir | G36: Prof. Dr. Mohd Rafi bin Yaacob | H36: Fakulti Keusahawanan dan Perniagaan | N36: PRA PEPERIKSAAN LISAN (PRE VIVA VOCE) | O36: YBhg. Prof./Prof. Madya/Dr. | P36: YBhg. Prof./Prof. Madya/Dr. | Q36: Mesyuarat Jawatankuasa Pascasiswazah Bil. 7/2024 (kali ke-48) | S36: Pra Peperiksaan Lisan (Pre Viva Voce) | T36: Doktor Falsafah | U36: Perakaunan | V36: Agustiawan | W36: A19E0011F | X36: Internal Audit Behavioral, Job Performance, and Audit Quality of Local Government In Riau Province | Y36: 12 Ogos 2024 (Isnin) | Z36: 2.30 petang | AA36: Platform Zoom (pautan akan dimaklumkan kemudian) | AB36: 1) Prof. Dr. Mohd Nor Hakimin bin Yusoff (Penyelia Utama) | AC36: 2) Dr. Tahirah binti Abdullah (Penyelia Bersama)
A37: 36 | C37: OKTOBER | D37: Dr. Shah Iskandar Fahmie bin Ramlee | E37: Dr. Siti Salwani binti Abdullah | F37: Prof. Dr. Mohd Rafi bin Yaacob | G37: Prof. Madya Ts. Dr. Zuraimi bin Abdul Aziz | H37: Fakulti Keusahawanan dan Perniagaan | N37: PRA PEPERIKSAAN LISAN (PRE VIVA VOCE) | O37: YBhg. Prof./Prof. Madya/Dr. | P37: YBhg. Prof./Prof. Madya/Dr. | Q37: Mesyuarat Jawatankuasa Pascasiswazah Bil. 7/2024 (kali ke-48) | S37: Pra Peperiksaan Lisan (Pre Viva Voce) | T37: Doktor Falsafah | U37: Pengurusan | V37: Azianis binti Mohd Noor | W37: A14E019F | X37: Organization Capital, Human Capital, Members Participation, Government Support and Co-operative Performance: Moderating Effect of Leadership | Y37: 21 Oktober 2024 (Isnin) | Z37: 10.00 pagi | AA37: Platform Zoom (pautan akan dimaklumkan kemudian) | AB37: 1) Prof. Dr. Mohammad bin Ismail (Penyelia Utama) | AC37: 2) Prof. Dr. Mohd Nor Hakimin bin Yusoff (Penyelia Bersama) | AE37: Pengerusi - Prof. Madya Dr. Dzulkifli bin Mukhtar (Tukar)
A38: 37 | C38: OGOS | D38: Dr. Kasmaruddin bin Che Hussin | E38: Dr. Siti Fariha binti Muhamad | F38: Prof. Dr. Mohd Rafi bin Yaacob | G38: Dr. Nor Hafiza binti Othman | H38: Fakulti Keusahawanan dan Perniagaan | N38: PRA PEPERIKSAAN LISAN (PRE VIVA VOCE) | O38: YBhg. Prof./Dr. | P38: YBhg. Prof./Dr. | Q38: Mesyuarat Jawatankuasa Pascasiswazah Bil. 7/2024 (kali ke-48) | S38: Pra Peperiksaan Lisan (Pre Viva Voce) | T38: Doktor Falsafah | U38: Keusahawanan | V38: Muhammad Nizam bin Zainuddin | W38: A19E056F | X38: The Development of Entrepreneurial Passion in the Identity Workspace of the Postgraduate Entrepreneurship Education Program | Y38: 10 September 2024 (Selasa) | Z38: 10.00 pagi | AA38: Platform Zoom (pautan akan dimaklumkan kemudian) | AB38: 1) Prof. Madya Dr. Dzulkifli bin Mukhtar (Penyelia Utama) | AC38: 2) Prof. Madya Dr. Anis Amira binti Ab Rahman (Penyelia Bersama) | AE38: Pengerusi - Prof. Madya Dr. Hazriah binti Hasan (Tukar) Pen. Pengerusi - Dr. Rikinorhakis bin Ridzwan (Tukar)
A39: 38 | C39: OGOS | D39: Dr. Azira Hanani binti Berahim @ Ab Rahman | F39: Prof. Madya Dr. Dzulkifli bin Mukhtar | G39: Dr. Tahirah binti Abdullah | H39: Fakulti Keusahawanan dan Perniagaan | N39: PRA PEPERIKSAAN LISAN (PRE VIVA VOCE) | O39: YBhg. Prof./Prof. Madya/Dr. | P39: YBhg. Prof. Madya/Dr. | S39: Pra Peperiksaan Lisan (Pre Viva Voce) | T39: Doktor Falsafah | U39: Perakaunan | V39: Linda Hetri Suriyanti | W39: A20E0183F | X39: The Mediating Effects of Innovation and a Dynamic Environment on the Link Between Strategic Management Accounting Techniques and Performance in Riau Manufacturing Companies | Y39: Akan ditentukan oleh penyelia | Z39: Akan ditentukan oleh penyelia | AA39: Akan ditentukan oleh penyelia | AB39: 1) Prof. Madya Dr. Noorul Azwin binti Md Nasir (Penyelia Utama) | AC39: 2) Dr. Siti Afiqah binti Zainuddin (Penyelia Bersama)
A40: 39 | C40: OGOS | D40: Dr. Wan Mohd Nazdrol bin Wan Mohd Nasir | E40: Dr. Suhaila binti Abdul Kadir | F40: Prof. Madya Dr. Wan Farha binti Wan Zulkiffli | G40: Dr. Nik Syuhailah binti Nik Hussin | H40: Fakulti Keusahawanan dan Perniagaan | N40: PRA PEPERIKSAAN LISAN (PRE VIVA VOCE) | O40: YBhg. Prof./Prof. Madya/Dr. | P40: YBhg. Prof. Madya/Dr. | S40: Pra Peperiksaan Lisan (Pre Viva Voce) | T40: Doktor Falsafah | U40: Pemasaran | V40: Wang Peijing | W40: A21E038F | X40: The Relationship Between Brand Image, Brand Attachment, Brand Hate and Brand Relationship Quality in Xiaomi Virtual Communities | Y40: 4 September 2024 (Rabu) | Z40: 9.30 pagi | AA40: Akan ditentukan oleh penyelia | AB40: 1) Prof. Madya Dr. Noor Hasmini binti Abd Ghani (Penyelia Utama) | AC40: 2) Dr. Nur Izzati binti Mohamad Anuar (Penyelia Bersama)
A41: 40 | C41: SEPTEMBER | D41: Prof. Madya. Dr. Mohd Zulkifli bin Muhammad | E41: En. Syed Azlan Aljaffree bin Syed Khadzil | F41: Dr. Amira binti Jamil | G41: Dr. Siti Fariha binti Muhamad | H41: Fakulti Keusahawanan dan Perniagaan | N41: PENILAIAN CADANGAN PENYELIDIKAN (PROPOSAL DEFENSE) | O41: YBrs. Dr. | P41: YBrs. Dr. | Q41: Mesyuarat Jawatankuasa Pascasiswazah Bil. 8/2024 (kali ke-49) | S41: Penilaian Cadangan Penyelidikan (Proposal Defense) | T41: Doktor Falsafah | U41: Perakaunan | V41: Tobi Arfan | W41: A22E146F | X41: Pricing Strategy Of Riau Private Polytechnic Higher Education: A Cost And Value-Based Perspective | Y41: 2 Oktober 2024 (Rabu) | Z41: 10.00 pagi | AA41: Platform Zoom (pautan akan dimaklumkan kemudian) | AB41: 1) Dr. Mohd Rushdan bin Yasoa’ (Penyelia Utama) | AC41: 2) Dr. Siti Afiqah binti Zainuddin (Penyelia Bersama) | AD41: 3) Dr. Mardhiah binti Kamaruddin (Penyelia Bersama) | AE41: Pengerusi - Dr. Tahirah binti Abdullah (Tukar)
A42: 41 | C42: SEPTEMBER | D42: Dr. Tahirah binti Abdullah | E42: En. Mohamed Ariff bin Abdul Rahman | F42: Prof. Dr. Mohd Nor Hakimin bin Yusoff | G42: Dr. Zaminor binti Zamzamir @ Zamzamin | H42: Fakulti Keusahawanan dan Perniagaan | N42: PENILAIAN CADANGAN PENYELIDIKAN (PROPOSAL DEFENSE) | O42: YBhg. Prof./Dr. | P42: YBhg. Prof./Dr. | Q42: Mesyuarat Jawatankuasa Pascasiswazah Bil. 8/2024 (kali ke-49) | S42: Penilaian Cadangan Penyelidikan (Proposal Defense) | T42: Doktor Falsafah | U42: Perakaunan | V42: Yefni | W42: A22E150F | X42: Corporate Governance as a Moderating Variable Between Earning Management and Company Value | Y42: 26 September 2024 (Khamis) | Z42: 10.00 pagi | AA42: Platform Zoom (pautan akan dimaklumkan kemudian) | AB42: 1) Prof. Madya Dr. Noorul Azwin binti Md Nasir (Penyelia Utama) | AC42: 2) Dr. Siti Fariha binti Muhamad (Penyelia Bersama)
A43: 42 | C43: OKTOBER | D43: Dr. Norfazlirda binti Hairani | E43: Puan Nadia Hanum binti Amiruddin | F43: Prof. Madya Dr. Noor Hasmini binti Abd Ghani | G43: Dr. Nik Syuhailah binti Nik Hussin | H43: Fakulti Keusahawanan dan Perniagaan | N43: PENILAIAN CADANGAN PENYELIDIKAN (PROPOSAL DEFENSE) | O43: YBrs. Prof. Madya/Dr. | P43: YBrs. Prof. Madya/Dr. | Q43: Mesyuarat Jawatankuasa Pascasiswazah Bil. 8/2024 (kali ke-49) | S43: Penilaian Cadangan Penyelidikan (Proposal Defense) | T43: Doktor Falsafah | U43: Pemasaran | V43: Wu QianYing | W43: A21E055F | X43: Factors Influencing Consumers’ Coffee Purchase Intention in China: The Mediating Effect of Satisfaction | Y43: 20 November 2024 (Rabu) | Z43: 10.00 pagi | AA43: Platform Zoom (pautan akan dimaklumkan kemudian) | AB43: 1) Prof. Dr. Mohammad bin Ismail (Penyelia Utama) | AE43: Penal 1 - Prof. Madya Dr. Wan Farha binti Wan Zulkiffli (tukar)
A44: 43 | C44: SEPTEMBER | D44: Dr. Suhaila binti Abdul Kadir | E44: Dr. Mohamad Hazeem bin Mohmad Sidik | F44: Prof. Madya Dr. Dzulkifli bin Mukhtar | G44: Dr. Syamsuriana binti Sidek | H44: Fakulti Keusahawanan dan Perniagaan | N44: PRA PEPERIKSAAN LISAN (PRE VIVA VOCE) | O44: YBrs. Prof. Madya/Dr. | P44: YBrs. Prof. Madya/Dr. | Q44: Mesyuarat Jawatankuasa Pascasiswazah Bil. 9/2024 (kali ke-50) | S44: Pra Peperiksaan Lisan (Pre Viva Voce) | T44: Doktor Falsafah | U44: Keusahawanan | V44: Nurul Faizah binti Halim | W44: A21E030P | X44: The Internal and Externel Factors of Franchisee Survivability: The Mediating Role of Market Orientation | Y44: 14 Oktober 2024 (Isnin) | Z44: 10.00 pagi | AA44: Platform Zoom (pautan akan dimaklumkan kemudian) | AB44: 1) Prof. Madya Ts. Dr. Zuraimi bin abdul Aziz (Penyelia Utama) | AC44: 2) Dr. Norhafiza binti Othman (Penyelia Bersama) | AD44: 3) Dr. Nor Ashykin binti Abdul Aziz (Penyelia Bersama) | AE44: Pengerusi - Prof. Madya Dr. Muhamad Saufi bin Che Rusuli (Tukar)
A45: 44 | C45: OKTOBER | D45: Prof. Madya Dr. Muhammad Ashlyzan bin Razik | E45: Dr. Lu Man Hong | F45: Prof. Madya Dr. Noorshella binti Che Nawi | G45: Dr. Norzalizah binti Bahari | H45: Fakulti Keusahawanan dan Perniagaan | N45: PENILAIAN CADANGAN PENYELIDIKAN (PROPOSAL DEFENSE) | O45: YBrs. Prof. Madya/Dr. | P45: YBrs. Prof. Madya/Dr. | Q45: Mesyuarat Jawatankuasa Pascasiswazah Bil. 9/2024 (kali ke-50) | S45: Penilaian Cadangan Penyelidikan (Proposal Defense) | T45: Doktor Falsafah | U45: Pengurusan | V45: Salini Aina binti Mamat | W45: A23D043F | X45: Entrepreneurial Capabilities Abortive Capacity and Support Intervention Towards Cyberpreneurship Improvement of MICRO Entrepreneurs in Kelantan | Y45: 17 Oktober 2024 (Khamis) | Z45: 10.00 pagi | AA45: Platform Zoom (pautan akan dimaklumkan kemudian) | AB45: 1) Prof. Madya. Ts. Dr. Zailani bin Abdullah (Penyelia Utama) | AC45: 2) Dr. Nor Hafiza binti Othman (Penyelia Bersama) | AD45: 3) Dr. Mohd Safwan bin Ghazali (Penyelia Bersama)
A46: 45 | C46: OKTOBER | D46: Dr. Kasmaruddin bin Che Hussin | E46: En. Mohamed Ariff bin Abdul Rahman | F46: Prof. Dr. Mohd Rafi bin Yaacob | G46: Dr. Tahirah binti Abdullah | H46: Fakulti Keusahawanan dan Perniagaan | N46: PRA PEPERIKSAAN LISAN (PRE VIVA VOCE) | O46: YBhg. Prof./Prof. Madya/Dr. | P46: YBhg. Prof./Prof. Madya/Dr. | Q46: Mesyuarat Jawatankuasa Pascasiswazah Bil. 10/2024 (kali ke-51) | S46: Pra Peperiksaan Lisan (Pre Viva Voce) | T46: Doktor Falsafah | U46: Perakaunan | V46: Wu Shuangshuang | W46: A21E054F | X46: Study on the Effect of Preferential Tax Policies on Science and Technology Capital | Y46: 23 Oktober 2024 (Rabu) | Z46: 10.00 pagi | AA46: Platform Zoom (pautan akan dimaklumkan kemudian) | AB46: 1) Prof. Dr. Mohd Nor Hakimin bin Yusof (Penyelia Utama) | AE46: Pengerusi - Prof. Madya Dr. Dzulkifli bin Mukhtar (Tukar)
A47: 46 | C47: OKTOBER | D47: Prof. Dr. Balakrishnan a/l Parasuraman | E47: Dr. Hazrina binti Hasbolah | F47: Prof. Madya. Ts. Dr. Zailani bin Abdullah | G47: Prof. Madya Dr. Muhamad Saufi bin Che Rusuli | H47: Fakulti Keusahawanan dan Perniagaan | N47: PRA PEPERIKSAAN LISAN (PRE VIVA VOCE) | O47: YBhg. Prof./Prof. Madya/Dr. | P47: YBhg. Prof./Prof. Madya/Dr. | Q47: Mesyuarat Jawatankuasa Pascasiswazah Bil.10/2024 (kali ke-51) | S47: Pra Peperiksaan Lisan (Pre Viva Voce) | T47: Doktor Falsafah | U47: Pengurusan | V47: Risnal Diansyah | W47: A19E0009F | X47: The Factors Influencing E-Learning Adoption Behaviour in Indonesia | Y47: 10 November 2024 (Ahad) | Z47: 10.00 pagi | AA47: Platform Zoom (pautan akan dimaklumkan kemudian) | AB47: 1) Prof. Madya Dr. Noorshella binti Che Nawi (Penyelia Utama) | AC47: 2) Dr. Siti Afiqah binti Zainuddin (Penyelia Bersama)
A48: 47 | C48: OKTOBER | D48: Prof. Madya Dr. Muhamad Saufi bin Che Rusuli | E48: Dr. Norhafifah binti Samsudin | F48: Dr. Suhaila binti Abdul Kadir | G48: Dr. Mohd Ikhwan bin Aziz | H48: Fakulti Keusahawanan dan Perniagaan | N48: PENILAIAN CADANGAN PENYELIDIKAN (PROPOSAL DEFENSE) | O48: YBrs. Dr. | P48: YBrs. Dr. | Q48: Mesyuarat Jawatankuasa Pascasiswazah Bil.10/2024 (kali ke-51) | S48: Penilaian Cadangan Penyelidikan (Proposal Defense) | T48: Doktor Falsafah | U48: Pengurusan | V48: Enny Widayati | W48: A22E120F | X48: Factor Influences the Business Financing of Small and Medium Manufacturing Industry In Indonesia | Y48: 11 November 2024 (Isnin) | Z48: 10.00 pagi | AA48: Platform Zoom (pautan akan dimaklumkan kemudian) | AB48: 1) Prof. Madya Ts. Dr. Zuraimi bin abdul Aziz (Penyelia Utama) | AC48: 2) Prof. Madya Dr. Dzulkifli bin Mukhtar (Penyelia Bersama) | AE48: Penolong Pengerusi - Dr. Nur Syakirah binti Ahmad (tukar)
A49: 48 | C49: OKTOBER | D49: Dr. Syarizal bin Abdul Rahim | E49: Dr. Siti Som binti Husin | F49: Dr. Suhaila binti Abdul Kadir | G49: Dr. Nor Hafiza binti Othman | H49: Fakulti Keusahawanan dan Perniagaan | N49: PENILAIAN CADANGAN PENYELIDIKAN (PROPOSAL DEFENSE) | O49: YBrs. Dr. | P49: YBrs. Dr. | Q49: Mesyuarat Jawatankuasa Pascasiswazah Bil.10/2024 (kali ke-51) | S49: Penilaian Cadangan Penyelidikan (Proposal Defense) | T49: Doktor Falsafah | U49: Pengurusan | V49: Mu Zongliang | W49: A22E006F | X49: Linkage Between Entrepreneurship Education Towards Entrepreneurial Intention Among College Students in China | Y49: 28 November 2024 (Khamis) | Z49: 10.00 pagi | AA49: Platform Zoom (pautan akan dimaklumkan kemudian) | AB49: 1) Prof. Madya Dr. Muhamad Saufi bin Che Rusuli (Penyelia Utama) | AC49: 2) Dr. Wan Mohd Nazdrol bin Wan Mohd Nasir (Penyelia Bersama)
A50: 49 | C50: OKTOBER | D50: Dr. Amira binti Jamil | E50: Dr. Nurul Muna binti Mohamad | F50: Prof. Madya. Ts. Dr. Zailani bin Abdullah | G50: Dr. Mohd Ikhwan bin Aziz | H50: Fakulti Keusahawanan dan Perniagaan | N50: PENILAIAN CADANGAN PENYELIDIKAN (PROPOSAL DEFENSE) | O50: YBrs. Prof. /Dr. | P50: YBrs. Prof. /Dr. | Q50: Mesyuarat Jawatankuasa Pascasiswazah Bil.10/2024 (kali ke-51) | S50: Penilaian Cadangan Penyelidikan (Proposal Defense) | T50: Doktor Falsafah | U50: Pengurusan | V50: Ma Jiqiang | W50: A20E045F | X50: The effect of talent management on sales team management performance in Chinese small and medium-sized FMCG firms: the mediating role of leadership style | Y50: 26 November 2024 (Selasa) | Z50: 2.30 petang | AA50: Platform Zoom (pautan akan dimaklumkan kemudian) | AB50: 1) Dr. Nur Izzati binti Mohamad Anuar (Penyelia Utama) | AC50: 2) Dr. Tan Wai Hong (Penyelia Bersama) | AE50: Pengerusi - Dr. Muhammad Jaffri bin Mohd Nasir (Tukar) Pen. Pengerusi - Dr. Amira binti Jamil (Tukar) Panel I - Prof. Dr. Balakrishnan a/l Parasuraman (Tukar)
A51: 50 | C51: OKTOBER | D51: Prof. Dr. Balakrishnan a/l Parasuraman | E51: Dr. Hazrina binti Hasbolah | F51: Prof. Madya Dr. Muhamad Saufi bin Che Rusuli | G51: Prof. Madya Dr. Hazriah binti Hasan | H51: Fakulti Keusahawanan dan Perniagaan | N51: PRA PEPERIKSAAN LISAN (PRE VIVA VOCE) | O51: YBhg. Prof./Prof. Madya/Dr. | P51: YBhg. Prof./Prof. Madya/Dr. | Q51: Mesyuarat Jawatankuasa Pascasiswazah Bil.11/2024 (kali ke-52) | S51: Penilaian Cadangan Penyelidikan (Proposal Defense) | T51: Doktor Falsafah | U51: Pengurusan | V51: Rudy Asrianto | W51: A19E0034F | X51: Organization Palm Oil Mills Sustainable Competitive Advantage Through Big Data Analytics Capability In Riau Province | Y51: 10 November 2024 (Ahad) | Z51: 11.00 pagi | AA51: Platform Zoom (pautan akan dimaklumkan kemudian) | AB51: 1) Prof. Madya. Ts. Dr. Zailani bin Abdullah (Penyelia Utama)
A52: 51 | C52: DISEMBER | D52: Dr. Siti Salwani binti Abdullah | E52: Dr. Muhammad Firdaus bin Zakaria | F52: Dr. Mohd Rushdan bin Yasoa’ | G52: Dr. Siti Fariha binti Muhamad | H52: Fakulti Keusahawanan dan Perniagaan | M52: DOKTOR FALSAFAH | N52: PENILAIAN CADANGAN PENYELIDIKAN (PROPOSAL DEFENSE) | O52: YBrs. Dr. | P52: YBrs. Dr. | Q52: Mesyuarat Jawatankuasa Pascasiswazah Bil.11/2024 (kali ke-52) | S52: Penilaian Cadangan Penyelidikan (Proposal Defense) | T52: Doktor Falsafah | U52: Perakaunan | V52: Nifateehah Pattanawong | W52: A19E043F | X52: The Impact of Quality Financial Accounting Information on Decision-making and Business Performance among SMEs. | Y52: 24 Disember 2024 (Selasa) | Z52: 2.30 petang | AA52: Platform Zoom (pautan akan dimaklumkan kemudian) | AB52: 1) Dr. Ainon @ Jamilah binti Ramli (Penyelia Utama) | AC52: 2) Prof. Dr. Mohd Nor Hakimin bin Yusoff (Penyelia Bersama) | AD52: 3) Dr. Siti Afiqah binti Zainuddin (Penyelia Bersama)
A53: 52 | C53: DISEMBER | D53: Dr. Norzalizah binti Bahari | E53: Dr. Hazrina binti Hasbolah | F53: Prof. Madya Dr. Mohd Nazri bin Zakaria | G53: Dr. Nur Izzati binti Mohamad Anuar | H53: Fakulti Keusahawanan dan Perniagaan | M53: SARJANA KEUSAHAWANAN | N53: PENILAIAN CADANGAN PENYELIDIKAN (PROPOSAL DEFENSE) | O53: YBrs. Prof. Madya/Dr. | P53: YBrs. Prof. Madya/Dr. | Q53: Mesyuarat Jawatankuasa Pascasiswazah Bil.11/2024 (kali ke-52) | S53: Penilaian Cadangan Penyelidikan (Proposal Defense) | T53: Sarjana Keusahawanan | U53: Pengurusan | V53: Innocent Arinze | W53: A23D059F | X53: A Study of Different Cultural background and Societal Norm Influence Entrepreneurial Behavior and Success Rates in Kelantan | Y53: 23 Disember 2024 (Isnin) | Z53: 2.30 petang | AA53: Platform Zoom (pautan akan dimaklumkan kemudian) | AB53: 1) Dr. Hasannuddiin bin Hassan (Penyelia Utama) | AC53: 2) Dr. Siti Rohana binti Mohamad (Penyelia Bersama) | AD53: 3) Dr. Hanieh Alipour Bazkiaei (Penyelia Bersama) | AE53: Pengerusi - Dr. Nur Syafiqah binti A. Samad (tukar)
A54: 53 | C54: DISEMBER | D54: Dr. Nur Izzati binti Mohamad Anuar | E54: Dr. Azira Hanani binti Berahim @ Ab Rahman | F54: Prof. Madya Dr. Anis Amira binti Ab Rahman | G54: Dr. Norzalizah binti Bahari | H54: Fakulti Keusahawanan dan Perniagaan | L54: SEMULA | M54: DOKTOR FALSAFAH | N54: PENILAIAN SEMULA CADANGAN PENYELIDIKAN (RE-PROPOSAL DEFENSE) | O54: YBrs. Prof. Madya/Dr. | P54: YBrs. Prof. Madya/Dr. | Q54: Mesyuarat Jawatankuasa Pascasiswazah Bil.11/2024 (kali ke-52) | R54: Sesi Penilaian Semula | S54: Penilaian Semula Cadangan Penyelidikan (re-Proposal Defense) | T54: Doktor Falsafah | U54: Pengurusan | V54: Norrini binti Muhammad | W54: A16E081P | X54: Determinants Factors of Entrepreneurial Intention and Entrepreneurial Behavior Towards Student Entrepreneurs in Malaysia Higher Education Institutions | Y54: 5 Januari 2025 (Ahad) | Z54: 2.30 petang | AA54: Platform Zoom (pautan akan dimaklumkan kemudian) | AB54: 1) Prof. Madya Dr. Muhamad Saufi bin Che Rusuli (Penyelia Utama)
A55: 54 | C55: DISEMBER | D55: Dr. Nur Ain Ayuni binti Sabri | F55: Prof. Madya. Ts. Dr. Zailani bin Abdullah | G55: Prof. Madya Dr. Wan Farha binti Wan Zulkiffli | H55: Fakulti Keusahawanan dan Perniagaan | M55: SARJANA KEUSAHAWANAN | N55: PRA PEPERIKSAAN LISAN (PRE VIVA VOCE) | O55: YBrs. Prof. Madya/Dr. | P55: YBrs. Prof. Madya/Dr. | Q55: Mesyuarat Jawatankuasa Pascasiswazah Bil.12/2024 (kali ke-53) | S55: Pra Peperiksaan Lisan (Pre Viva Voce) | T55: Sarjana Keusahawanan | U55: Pengurusan Sumber Manusia | V55: Antony Barubui | W55: A20D070F | X55: Kebolehpasaran Graduan IPTA Dalam Sektor Koperasi di Negeri Sabah | Y55: 5 Disember 2024 (Khamis) | Z55: 10.00 pagi | AA55: Platform Zoom (pautan akan dimaklumkan kemudian) | AB55: 1) Prof. Dr. Balakrishnan a/l Parasuraman (Penyelia Utama)
A56: 55 | C56: DISEMBER | D56: En. Muhammad Naqib bin Mat Yunoh | F56: Dr. Mohd Ikhwan bin Aziz | G56: Prof. Madya Dr. Dzulkifli bin Mukhtar | H56: Fakulti Keusahawanan dan Perniagaan | M56: SARJANA KEUSAHAWANAN | N56: PRA PEPERIKSAAN LISAN (PRE VIVA VOCE) | O56: YBrs. Prof. Madya/Dr. | P56: YBrs. Prof. Madya/Dr. | Q56: Mesyuarat Jawatankuasa Pascasiswazah Bil.12/2024 (kali ke-53) | S56: Pra Peperiksaan Lisan (Pre Viva Voce) | T56: Sarjana Keusahawanan | U56: Pengurusan | V56: Nur Ain Amirah binti Mohd Nazli | W56: A22D051F | X56: An In-Depth Exploration of Innovative Food Waste Management Practices at Pasar Siti Khadijah | Y56: 31 Disember 2024 (Selasa) | Z56: 2.30 petang | AA56: Bilik IVL, UMK Kampus Kota | AB56: 1) Dr. Hana Yazmeen binti Hapiz (Penyelia Utama) | AC56: 2) Dr. Mohd Safwan bin Ghazali (Penyelia Bersama)
A57: 56 | B57: 2025 | C57: JANUARI | D57: Prof. Madya Dr. Noor Hasmini binti Abd Ghani | E57: Dr. Hazrina binti Hasbolah | F57: Prof. Madya Dr. Dzulkifli bin Mukhtar | G57: Prof. Madya. Dr. Mohd Zulkifli bin Muhammad | H57: Fakulti Keusahawanan dan Perniagaan | M57: DOKTOR FALSAFAH | N57: PENILAIAN CADANGAN PENYELIDIKAN (PROPOSAL DEFENSE) | O57: YBhg. Prof. / Prof. Madya/Dr. | P57: YBhg. Prof. / Prof. Madya/Dr. | Q57: Mesyuarat Jawatankuasa Pascasiswazah Bil.12/2024 (kali ke-53) | S57: Penilaian Cadangan Penyelidikan (Proposal Defense) | T57: Doktor Falsafah | U57: Keusahawanan | V57: Mohd Hafizuddin bin Mejah | W57: A21E062P | X57: Corak Pemikiran Kepimpinan TYT Tun Setia (Dr) Haji Mohd Ali bin Rustam, Yang Di-Pertua Negri Melaka | Y57: 21 Januari 2025 | Z57: 10.00 pagi | AA57: Platform Zoom (pautan akan dimaklumkan kemudian) | AB57: 1) Prof. Dr. Mohammad bin Ismail (Penyelia Utama) | AC57: 2) Dr. Siti Amaliya binti Mohd Radyi (Penyelia Bersama) | AE57: Pengerusi - Prof. Dr. Balakrishnan a/l Parasuraman (Tukar)
A58: 57 | C58: FEBRUARI | D58: Prof. Madya. Dr. Mohd Zulkifli bin Muhammad | E58: Dr. Muhammad Firdaus bin Zakaria | F58: Dr. Wan Mohd Nazdrol bin Wan Mohd Nasir | G58: Dr. Nur Syakirah binti Ahmad | H58: Fakulti Keusahawanan dan Perniagaan | M58: DOKTOR FALSAFAH | N58: PRA PEPERIKSAAN LISAN (PRE VIVA VOCE) | O58: YBrs. Prof. Madya/Dr. | P58: YBrs. Prof. Madya/Dr. | Q58: Mesyuarat Jawatankuasa Pascasiswazah Bil.1/2025 (kali ke-54) | S58: Pra Peperiksaan Lisan (Pre Viva Voce) | T58: Doktor Falsafah | U58: Pemasaran | V58: Lydia Hidayu binti Lily Suhairi | W58: A17E064P | X58: E-CRM, Social Mesdia Marketing and E-Brand Equity in Hotel Industry Context: The Mediating Effect of E-Brand Experience | Y58: 16 Februari 2025 (Ahad) | Z58: 10.30 pagi | AA58: Platform Zoom (pautan akan dimaklumkan kemudian) | AB58: 1) Prof. Madya Dr. Noor Hasmini binti Abd Ghani (Penyelia Utama)
A59: 58 | C59: FEBRUARI | D59: Dr. Muhammad Zulfaris bin Mohd Salleh | E59: Dr. Nurul Muna binti Mohamad | F59: Prof. Madya. Dr. Mohd Zulkifli bin Muhammad | G59: Dr. Mohd Afifie bin Mohd Alwi | H59: Fakulti Keusahawanan dan Perniagaan | M59: SARJANA KEUSAHAWANAN | N59: PENILAIAN CADANGAN PENYELIDIKAN (PROPOSAL DEFENSE) | O59: YBrs. Prof. Madya/Dr. | P59: YBrs. Prof. Madya/Dr. | Q59: Mesyuarat Jawatankuasa Pascasiswazah Bil.1/2025 (kali ke-54) | S59: Penilaian Cadangan Penyelidikan (Proposal Defense) | T59: Sarjana Keusahawanan | U59: Kewangan Islam | V59: Siti Hanis binti Shamma | W59: A21D031F | X59: Literasi Kewangan Berdasarkan Konsep Maqasid Syariah: B40 di Kelantan | Y59: 20 Mac 2025 (Khamis) | Z59: 10.00 pagi | AA59: Platform Zoom (pautan akan dimaklumkan kemudian) | AB59: 1) Prof. Madya Dr. Azwan bin Abdullah (Penyelia Utama)
A60: 59 | C60: FEBRUARI | D60: Prof. Madya Dr. Hazriah binti Hasan | E60: En. Mohamed Ariff bin Abdul Rahman | F60: Prof. Madya Dr. Mohd Nazri bin Zakaria | G60: Dr. Nur Izzati binti Mohamad Anuar | H60: Fakulti Keusahawanan dan Perniagaan | M60: DOKTOR FALSAFAH | N60: PENILAIAN CADANGAN PENYELIDIKAN (PROPOSAL DEFENSE) | O60: YBrs. Prof. Madya/Dr. | P60: YBrs. Prof. Madya/Dr. | Q60: Mesyuarat Jawatankuasa Pascasiswazah Bil.1/2025 (kali ke-54) | S60: Penilaian Cadangan Penyelidikan (Proposal Defense) | T60: Doktor Falsafah | U60: Pengurusan Sumber Manusia | V60: Shalini a/p Raja Kapol | W60: A22E014F | X60: Examining Leadership Styles Among the Multi-level Marketing (MLM) Leaders in Malaysia | Y60: 13 Mac 2025 (Khamis) | Z60: 10.00 pagi | AA60: Platform Zoom (pautan akan dimaklumkan kemudian) | AB60: 1) Prof. Dr. Balakrishnan a/l Parasuraman (Penyelia Utama) | AC60: 2) Prof. Madya Dr. Dzulkifli bin Mukhtar (Penyelia Bersama) | AE60: Penolong Pengerusi - Dr. Siti Amaliya binti Mohd Radyi (Tukar)
A61: 60 | C61: FEBRUARI | D61: Prof. Madya Dr. Mohd Nazri bin Muhayiddin | E61: Dr. Muhammad Firdaus bin Zakaria | F61: Prof. Madya Dr. Hazriah binti Hasan | H61: Fakulti Keusahawanan dan Perniagaan | J61: Prof. Madya Dr. Roslizawati binti Che Aziz | K61: Fakulti Hospitaliti, Pelancongan dan Kesejahteraan | M61: DOKTOR FALSAFAH | N61: PENILAIAN CADANGAN PENYELIDIKAN (PROPOSAL DEFENSE) | O61: YBrs. Prof. Madya/Dr. | P61: YBrs. Prof. Madya/Dr. | Q61: Mesyuarat Jawatankuasa Pascasiswazah Bil.1/2025 (kali ke-54) | S61: Penilaian Cadangan Penyelidikan (Proposal Defense) | T61: Doktor Falsafah | U61: Kewangan | V61: Muhammad Ulin Nuha | W61: A23E082F | X61: Model Strategi Pembangunan Pelancongan Halal Mampan Melalui Pelancongan berasaskan Komuniti: Kajian di Kabupaten Pati, Jawa Tengah, Indonesia. | Y61: 9 Mac 2025 (Ahad) | Z61: 10.00 pagi | AA61: Platform Zoom (pautan akan dimaklumkan kemudian) | AB61: 1) Prof. Madya Dr. Mohd Zulkifli bin Muhammad (Penyelia Utama) | AC61: 2) Dr. Muhammad Zulfaris bin Mohd Salleh (Penyelia Bersama)
A62: 61 | C62: FEBRUARI | D62: Dr. Nur Farahiah binti Azmi | E62: Dr. Tahirah binti Abdullah | F62: Prof. Madya Dr. Azwan bin Abdullah | G62: Dr. Zaminor binti Zamzamir @ Zamzamin | H62: Fakulti Keusahawanan dan Perniagaan | M62: DOKTOR FALSAFAH | N62: PENILAIAN CADANGAN PENYELIDIKAN (PROPOSAL DEFENSE) | O62: YBrs. Prof. Madya/Dr. | P62: YBrs. Prof. Madya/Dr. | Q62: Mesyuarat Jawatankuasa Pascasiswazah Bil.1/2025 (kali ke-54) | S62: Penilaian Cadangan Penyelidikan (Proposal Defense) | T62: Doktor Falsafah | U62: Kewangan | V62: Zhang Yu | W62: A22E163F | X62: The Impact of Digital Financial Inclusion and Technological Innovation in the Financial Performance of SMEs: The Mediating Effect of Financing Constraints and Financing Structure | Y62: 4 Mac 2025 (Selasa) | Z62: 10.00 pagi | AA62: Platform Zoom (pautan akan dimaklumkan kemudian) | AB62: 1) Dr. Amira binti Jamil (Penyelia Utama) | AC62: 2) Dr. Ahmad Ridhuwan bin Abdullah (Penyelia Bersama)
A63: 62 | C63: FEBRUARI | D63: Dr. Mohd Afifie bin Mohd Alwi | E63: Dr. Siti Rohana binti Mohamad | F63: Prof. Dr. Mohd Nor Hakimin bin Yusoff | G63: Dr. Siti Fariha binti Muhamad | H63: Fakulti Keusahawanan dan Perniagaan | M63: DOKTOR FALSAFAH | N63: PENILAIAN CADANGAN PENYELIDIKAN (PROPOSAL DEFENSE) | O63: YBhg. Prof./Prof. Madya/Dr. | P63: YBhg. Prof./Prof. Madya/Dr. | Q63: Mesyuarat Jawatankuasa Pascasiswazah Bil.1/2025 (kali ke-54) | S63: Penilaian Cadangan Penyelidikan (Proposal Defense) | T63: Doktor Falsafah | U63: Perakaunan | V63: Dwi Jaya Kirana | W63: A24E3680F | X63: The Role of Sustainability Performance and External Sustainable Corporate Governance in Mitigating Earning Management | Y63: 8 April 2025 (Selasa) | Z63: 10.00 pagi | AA63: Platform Zoom (pautan akan dimaklumkan kemudian) | AB63: 1) Prof. Madya Dr. Mohd Zulkifli bin Muhammad (Penyelia Utama) | AC63: 2) Dr. Siti Salwani binti Abdullah (Penyelia Bersama) | AD63: 3) Dr. Ahmad Ridhuwan bin Abdullah (Penyelia Bersama)
A64: 63 | C64: FEBRUARI | D64: Dr. Amira binti Jamil | E64: Dr. Mohamad Zamhari bin Tahir | F64: Prof. Madya Dr. Dzulkifli bin Mukhtar | G64: Dr. Syamsuriana binti Sidek | H64: Fakulti Keusahawanan dan Perniagaan | M64: DOKTOR FALSAFAH | N64: PENILAIAN CADANGAN PENYELIDIKAN (PROPOSAL DEFENSE) | O64: YBrs. Prof. Madya/Dr. | P64: YBrs. Prof. Madya/Dr. | Q64: Mesyuarat Jawatankuasa Pascasiswazah Bil.1/2025 (kali ke-54) | S64: Penilaian Cadangan Penyelidikan (Proposal Defense) | T64: Doktor Falsafah | U64: Kewangan | V64: Mirza Hedismarlina Yuneline | W64: A23E061F | X64: The Adoption of Sustainability Practice Among Restaurant Entrepreneurs in Bandung Using Entrepreneurial Orientation and Digital Financial Inclusion as Moderator | Y64: 25 Mac 2025 (Selasa) | Z64: 10.00 pagi | AA64: Platform Zoom (pautan akan dimaklumkan kemudian) | AB64: 1) Prof. Dr. Mohd Nor Hakimin bin Yusof (Penyelia Utama) | AC64: 2) Dr. Siti Salwani binti Abdullah (Penyelia Bersama) | AE64: Pengerusi - Prof. Madya Dr. Dzulkifli bin Mukhtar (Tukar ker Panel 1) Panel 1 - Dr. Siti Fariha (Tukar)
A65: 64 | C65: FEBRUARI | D65: Prof. Madya Dr. Mohd Asrul Hery bin Ibrahim | E65: Dr. Nurul Muna binti Mohamad | F65: Prof. Madya. Dr. Mohd Zulkifli bin Muhammad | G65: Dr. Norzalizah binti Bahari | H65: Fakulti Keusahawanan dan Perniagaan | M65: DOKTOR FALSAFAH | N65: PENILAIAN CADANGAN PENYELIDIKAN (PROPOSAL DEFENSE) | O65: YBrs. Prof. Madya/Dr. | P65: YBrs. Prof. Madya/Dr. | Q65: Mesyuarat Jawatankuasa Pascasiswazah Bil.1/2025 (kali ke-54) | S65: Penilaian Cadangan Penyelidikan (Proposal Defense) | T65: Doktor Falsafah | U65: Pengurusan | V65: Aspiyati binti Jusoh | W65: A23E2784F | X65: Fostering the Entrepreneurs Capability in Sustaining The Halal Business Performance Focusing on Bumiputera MSMEe in East Coast of Malaysia. | Y65: 15 April 2025 (Rabu) | Z65: 10.00 pagi | AA65: Platform Zoom (pautan akan dimaklumkan kemudian) | AB65: 1) Prof. Madya Dr. Hazriah binti Hasan (Penyelia Utama) | AC65: 2) Dr. Mardhiah binti Kamaruddin (Penyelia Bersama) | AD65: 3) Dr. Wan Marhaini binti Wan Omar (Penyelia Luar)
A66: 65 | C66: FEBRUARI | D66: Dr. Kasmaruddin bin Che Hussin | E66: Dr. Nurul Fadzlyn binti Enche Nadzmy | F66: Prof. Madya Dr. Anis Amira binti Ab Rahman | G66: Dr. Hasannuddiin bin Hassan | H66: Fakulti Keusahawanan dan Perniagaan | M66: DOKTOR FALSAFAH | N66: PENILAIAN CADANGAN PENYELIDIKAN (PROPOSAL DEFENSE) | O66: YBrs. Prof. Madya/Dr. | P66: YBrs. Prof. Madya/Dr. | Q66: Mesyuarat Jawatankuasa Pascasiswazah Bil.1/2025 (kali ke-54) | S66: Penilaian Cadangan Penyelidikan (Proposal Defense) | T66: Doktor Falsafah | U66: Pengurusan | V66: Mochamad Purnomo | W66: A23E094F | X66: The Impact of Innovation and Collaboration on The Sustainable Performance of Small and Medium Enterprises in Indonesia: The Mediating Role of The Knowledge Management | Y66: 8 April 2025 (Selasa) | Z66: 10.00 pagi | AA66: Platform Zoom (pautan akan dimaklumkan kemudian) | AB66: 1) Dr. Shah Iskandar Fahmie bin Ramlee (Penyelia Utama) | AC66: 2) Dr. Ratih Pratiwi (Penyelia Luar) | AE66: Pengerusi - Prof. Madya Dr. Dzulkifli bin Mukhtar (Tukar)
A67: 66 | C67: FEBRUARI | D67: Dr. Norfazlirda binti Hairani | E67: Pn. Nurul Hasliana binti Hamsani | F67: Prof. Madya Dr. Noor Hasmini binti Abd Ghani | G67: Dr. Nik Syuhailah binti Nik Hussin | H67: Fakulti Keusahawanan dan Perniagaan | M67: DOKTOR FALSAFAH | N67: PENILAIAN CADANGAN PENYELIDIKAN (PROPOSAL DEFENSE) | O67: YBrs. Prof. Madya/Dr. | P67: YBrs. Prof. Madya/Dr. | Q67: Mesyuarat Jawatankuasa Pascasiswazah Bil.1/2025 (kali ke-54) | S67: Penilaian Cadangan Penyelidikan (Proposal Defense) | T67: Doktor Falsafah | U67: Pemasaran | V67: Jin Lili | W67: A21E006F | X67: Consumers Impulse Buying on Jewelry Products Through Live Streaming Commerce in China: A Mediating Role of Perceived Enjoyment | Y67: 16 April 2025 (Rabu) | Z67: 10.00 pagi | AA67: Platform Zoom (pautan akan dimaklumkan kemudian) | AB67: 1) Prof. Madya Dr. Wan Farha binti Wan Zulkiffli (Penyelia Utama)
A68: 67 | C68: FEBRUARI | D68: Dr. Nor Asma binti Ahmad | E68: Dr Nurnaddia binti Nordin | F68: Prof. Madya Dr. Noorul Azwin binti Md Nasir | G68: Dr. Nurhaiza binti Nordin | H68: Fakulti Keusahawanan dan Perniagaan | M68: DOKTOR FALSAFAH | N68: PENILAIAN CADANGAN PENYELIDIKAN (PROPOSAL DEFENSE) | O68: YBrs. Prof. Madya/Dr. | P68: YBrs. Prof. Madya/Dr. | Q68: Mesyuarat Jawatankuasa Pascasiswazah Bil.1/2025 (kali ke-54) | S68: Penilaian Cadangan Penyelidikan (Proposal Defense) | T68: Doktor Falsafah | U68: Kewangan | V68: Gao Wei | W68: A23E064F | X68: The Impact of ESG Practice, Government Subsidy, Managerial Ownership on Corporate Performance: Moderating with Economic Policy Uncertainty | Y68: 25 Mac 2025 (Selasa) | Z68: 2.30 petang | AA68: Platform Zoom (pautan akan dimaklumkan kemudian) | AB68: 1) Dr. Noor Raihani binti Zainol (Penyelia Utama) | AC68: 2) Dr. Siti Afiqah binti Zainuddin (Penyelia Bersama) | AD68: 3) Dr. Zaminor binti Zamzamir @ Zamzamin (Penyelia Bersama)
A69: 68 | C69: FEBRUARI | D69: Dr. Shah Iskandar Fahmie bin Ramlee | E69: Dr. Norzalizah binti Bahari | F69: Prof. Madya Dr. Mohd Nazri bin Zakaria | H69: Fakulti Keusahawanan dan Perniagaan | J69: Dr. Siti Amirah binti Ahmad Tarmizi | K69: Fakulti Pengajian Bahasa Dan Pembangunan Insan | M69: DOKTOR FALSAFAH | N69: PENILAIAN CADANGAN PENYELIDIKAN (PROPOSAL DEFENSE) | O69: YBrs. Prof. Madya/Dr. | P69: YBrs. Prof. Madya/Dr. | Q69: Mesyuarat Jawatankuasa Pascasiswazah Bil.1/2025 (kali ke-54) | S69: Penilaian Cadangan Penyelidikan (Proposal Defense) | T69: Doktor Falsafah | U69: Pengurusan | V69: Liu Liming | W69: A20E0139F | X69: Teachers’ Influence Mediate the Impact of Achievement Growth Performance among Local University Undergraduate Students in Jiangxi China | Y69: 9 April 2025 (Rabu) | Z69: 10.00 pagi | AA69: Platform Zoom (pautan akan dimaklumkan kemudian) | AB69: 1) Dr. Noor Raihani binti Zainol (Penyelia Utama) | AC69: 2) Prof. Dr. Naresh Kumar a/l Samy (Penyelia Bersama) | AD69: 3) Dr. Julia Tan Yin Yin (Penyelia Bersama) | AE69: Pengerusi - Dr. Nik Syuhailah binti Nik Hussin (Tukar)
A70: 69 | C70: MAC | D70: Dr. Muhammad Zulfaris bin Mohd Salleh | E70: Dr. Siti Rohana binti Mohamad | F70: Prof. Madya. Dr. Mohd Zulkifli bin Muhammad | G70: Dr. Mohd Afifie bin Mohd Alwi | H70: Fakulti Keusahawanan dan Perniagaan | M70: DOKTOR FALSAFAH | N70: PRA PEPERIKSAAN LISAN (PRE VIVA VOCE) | O70: YBrs. Prof. Madya/Dr. | P70: YBrs. Prof. Madya/Dr. | Q70: Mesyuarat Jawatankuasa Pascasiswazah Bil.2/2025 (kali ke-55) | S70: Pra Peperiksaan Lisan (Pre Viva Voce) | T70: Doktor Falsafah | U70: Perbankan dan Kewangan Islam | V70: Nusaibah binti Hilaluddin | W70: A20E0166F | X70: Ar-Rahn sebagai Sumber Dana Altarnatif Perusahaan Kecil dan Sederhana (PKS) berpandukan Aplikasi Maqasid Syariah | Y70: 14 April 2025 (Isnin) | Z70: 10.00 pagi | AA70: Platform Zoom (pautan akan dimaklumkan kemudian) | AB70: 1) Prof. Madya Dr. Azwan bin Abdullah (Penyelia Utama)
A71: 70 | C71: MAC | D71: Dr. Nur Ain Ayuni binti Sabri | E71: Dr. Siti Zamanira binti Mat Zaib | F71: Prof. Madya Dr. Anis Amira binti Ab Rahman | G71: Dr. Nor Hafiza binti Othman | H71: Fakulti Keusahawanan dan Perniagaan | M71: DOKTOR FALSAFAH | N71: PRA PEPERIKSAAN LISAN (PRE VIVA VOCE) | O71: YBrs. Prof. Madya/Dr. | P71: YBrs. Prof. Madya/Dr. | Q71: Mesyuarat Jawatankuasa Pascasiswazah Bil.2/2025 (kali ke-55) | S71: Pra Peperiksaan Lisan (Pre Viva Voce) | T71: Doktor Falsafah | U71: Keusahawanan | V71: Muhammad Fahimi bin Sofian | W71: A18E030F | X71: Implementation of Entrepreneural Apprenticeship-Based Learning Practice in Malaysian Higher Education Institutions | Y71: 7 April 2025 (Isnin) | Z71: 10.00 pagi | AA71: Platform Zoom (pautan akan dimaklumkan kemudian) | AB71: 1) Prof. Madya Dr. Dzulkifli bin Mukhtar (Penyelia Utama) | AE71: Pengerusi - Dr. Mohd Ikhwan bin Aziz (Tukar)
A72: 71 | C72: MAC | D72: Dr. Shah Iskandar Fahmie bin Ramlee | E72: Dr. Ahmad Ridhuwan bin Abdullah | F72: Prof. Madya Dr. Hazriah binti Hasan | G72: Dr. Noormariana binti Mohd Din | H72: Fakulti Keusahawanan dan Perniagaan | M72: DOKTOR FALSAFAH | N72: PRA PEPERIKSAAN LISAN (PRE VIVA VOCE) | O72: YBrs. Prof. Madya/Dr. | P72: YBrs. Prof. Madya/Dr. | Q72: Mesyuarat Jawatankuasa Pascasiswazah Bil.2/2025 (kali ke-55) | S72: Pra Peperiksaan Lisan (Pre Viva Voce) | T72: Doktor Falsafah | U72: Pengurusan | V72: Hammam Zaki | W72: A19E0027F | X72: The Effect of Organizational Citizenship Behaviour and Islamic Work Ethics on Relationships Between Islamic Leadership and Lecturers' Performance of Islamic Universities in Riau Province, Indonesia | Y72: 13 April 2025 (Ahad) | Z72: 10.00 pagi | AA72: Platform Zoom (pautan akan dimaklumkan kemudian) | AB72: 1) Prof. Dr. Naresh Kumar a/l Samy (Penyelia Utama) | AE72: Panel 1 - Prof. Madya Dr. Azwan bin Abdullah (Tukar) Panel 2 - Dr muhammad Zulfaris bin Mohd Salleh (Tukar)
A73: 72 | C73: MAC | D73: Dr. Tahirah binti Abdullah | E73: Dr. Tan Wai Hong | F73: Dr. Mohd Afifie bin Mohd Alwi | G73: Dr. Siti Rohana binti Mohamad | H73: Fakulti Keusahawanan dan Perniagaan | M73: DOKTOR FALSAFAH | N73: PRA PEPERIKSAAN LISAN (PRE VIVA VOCE) | O73: YBrs. Dr. | P73: YBrs. Dr. | Q73: Mesyuarat Jawatankuasa Pascasiswazah Bil.2/2025 (kali ke-55) | S73: Pra Peperiksaan Lisan (Pre Viva Voce) | T73: Doktor Falsafah | U73: Kewangan | V73: Song Ziyan | W73: A21E016F | X73: The Effects of Empathy and the Moderating Role of Regulatory Focus on Donors Decision to Support Philanthropic Crowdfunding in China | Y73: 27 Mac 2025 (Khamis) | Z73: 9.30 pagi | AA73: Platform Zoom (pautan akan dimaklumkan kemudian) | AB73: 1) Dr. Ahmad Ridhuwan bin Abdullah (Penyelia Utama) | AC73: 2) Dr. Siti Salwani binti Abdullah (Penyelia Bersama) | AD73: 3) Dr. Nur Farahiah binti Azmi (Penyelia Bersama)
A74: 73 | C74: MAC | D74: Prof. Madya Dr. Mohd Nazri bin Muhayiddin | E74: Dr. Siti Salwani binti Abdullah | F74: Prof. Madya Dr. Noorshella binti Che Nawi | G74: Prof. Madya Dr. Muhammad Ashlyzan bin Razik | H74: Fakulti Keusahawanan dan Perniagaan | M74: DOKTOR FALSAFAH | N74: PRA PEPERIKSAAN LISAN (PRE VIVA VOCE) | O74: YBrs. Prof. Madya/Dr. | P74: YBrs. Prof. Madya/Dr. | Q74: Mesyuarat Jawatankuasa Pascasiswazah Bil.2/2025 (kali ke-55) | S74: Pra Peperiksaan Lisan (Pre Viva Voce) | T74: Doktor Falsafah | U74: Pengurusan | V74: Mimi Zazira binti Hashim | W74: A16E069P | X74: Determinants of Digital Workplace Tools Adoption using Unified Theory of Acceptance and the Use of Technology Among Medium Enterprise Employees | Y74: 24 April 2025 (Khamis) | Z74: 10.00 pagi | AA74: Bilik Mesyuarat Pusat Antarabangsa (IO) | AB74: 1) Prof. Madya Dr. Muhamad Saufi bin Che Rusuli (Penyelia Utama)
A75: 74 | C75: MAC | D75: Dr. Syarizal bin Abdul Rahim | E75: Dr. Norhafifah binti Samsudin | F75: Dr. Mohd Ikhwan bin Aziz | G75: Dr. Noor Raihani binti Zainol | H75: Fakulti Keusahawanan dan Perniagaan | M75: DOKTOR FALSAFAH | N75: PRA PEPERIKSAAN LISAN (PRE VIVA VOCE) | O75: YBrs. Dr. | P75: YBrs. Dr. | Q75: Mesyuarat Jawatankuasa Pascasiswazah Bil.3/2025 (kali ke-56) | S75: Pra Peperiksaan Lisan (Pre Viva Voce) | T75: Doktor Falsafah | U75: Pengurusan | V75: Chen Zaidie | W75: A20E054F | X75: The Influence of PEC and CP towards Customer Intention ti Use Mobile Banking Applications in Hangzhou City Commercial Bank: The Mediating Effect of PEOU | Y75: 27 April 2025 (Ahad) | Z75: 10.00 pagi | AA75: Platform Zoom (pautan akan dimaklumkan kemudian) | AB75: 1) Dr. Fatihah binti Mohd (Penyelia Utama) | AC75: 2) Dr. Nur Ain Ayunni binti Sabri (Penyelia Bersama)
A76: 75 | C76: MAC | D76: Dr. Mohd Rushdan bin Yasoa’ | E76: En. Syed Azlan Aljaffree bin Syed Khadzil | F76: Prof. Dr. Mohd Nor Hakimin bin Yusoff | G76: Dr. Zaminor binti Zamzamir @ Zamzamin | H76: Fakulti Keusahawanan dan Perniagaan | M76: SARJANA KEUSAHAWANAN | N76: PRA PEPERIKSAAN LISAN (PRE VIVA VOCE) | O76: YBhg. Prof./Dr. | P76: YBhg. Prof./Dr. | Q76: Mesyuarat Jawatankuasa Pascasiswazah Bil.2/2025 (kali ke-55) | S76: Pra Peperiksaan Lisan (Pre Viva Voce) | T76: Sarjana Keusahawanan | U76: Perakaunan | V76: Endhyta Wisaksono | W76: A22D130F | X76: The Mediating Role of Integrated Reporting: Analyzing Firm Characteristics and Performance in Malaysian Public Firms | Y76: 20 April 2025 (Ahad) | Z76: 10.00 pagi | AA76: Platform Zoom (pautan akan dimaklumkan kemudian) | AB76: 1) Prof. Madya Dr. Noorul Azwin binti Md Nasir (Penyelia Utama) | AC76: 2) Dr. Amira binti Jamil (Penyelia Bersama) | AD76: 3) Dr. Siti Fariha binti Muhamad (Penyelia Bersama)
A77: 76 | C77: APRIL | D77: Dr. Nur Fadiah binti Mohd Zawawi | E77: Dr. Mohamad Hazeem bin Mohmad Sidik | F77: Prof. Madya Dr. Muhammad Ashlyzan bin Razik | G77: Dr. Kasmaruddin bin Che Hussin | H77: Fakulti Keusahawanan dan Perniagaan | M77: DOKTOR FALSAFAH | N77: PRA PEPERIKSAAN LISAN (PRE VIVA VOCE) | O77: YBrs. Prof. Madya/Dr. | P77: YBrs. Prof. Madya/Dr. | Q77: Mesyuarat Jawatankuasa Pascasiswazah Bil.3/2025 (kali ke-56) | S77: Pra Peperiksaan Lisan (Pre Viva Voce) | T77: Doktor Falsafah | U77: Keusahawanan | V77: Weerasak Sojipun | W77: A19E042F | X77: Factors Influence Toward Competitive Advantage of Logistic Service Providers in Saouthern of Thailand | Y77: 29 April 2025 (Selasa) | Z77: 10.00 pagi | AA77: Platform Zoom (pautan akan dimaklumkan kemudian) | AB77: 1) Prof. Madya Ts. Dr. Zuraimi bin abdul Aziz (Penyelia Utama) | AC77: 2) Dr. Rosmaizura binti Mohd Zain (Penyelia Bersama)
A78: 77 | C78: APRIL | D78: Prof. Madya. Dr. Mohd Zulkifli bin Muhammad | E78: Dr. Rikinorhakis bin Ridzwan | F78: Prof. Dr. Mohd Nor Hakimin bin Yusoff | G78: Dr. Suhaila binti Abdul Kadir | H78: Fakulti Keusahawanan dan Perniagaan | M78: DOKTOR FALSAFAH | N78: PENILAIAN CADANGAN PENYELIDIKAN (PROPOSAL DEFENSE) | O78: YBhg. Prof./Prof. Madya/Dr. | P78: YBhg. Prof./Prof. Madya/Dr. | Q78: Mesyuarat Jawatankuasa Pascasiswazah Bil.2/2025 (kali ke-55) | S78: Penilaian Cadangan Penyelidikan (Proposal Defense) | T78: Doktor Falsafah | U78: Keusahawanan | V78: Hasry Sham bin Chasmen | W78: A23E0778F | X78: Faktor Mempengaruhi Kejayaan Usahawan Muda Dalam Perniagaan Berasaskan Kerajaan Di Malaysia | Y78: 15 Mei 2025 (Khamis) | Z78: 10.00 pagi | AA78: Platform Zoom (pautan akan dimaklumkan kemudian) | AB78: 1) Prof. Dr. Mohammad bin Ismail (Penyelia Utama) | AC78: 2) Dr. Mohd Ikhwan bin Aziz (Penyelia Bersama) | AE78: Pengerusi - Prof. Madya Dr. Dzulkifli bin Mukhtar (tukar - Bercuti)
A79: 78 | C79: APRIL | D79: Dr. Mohd Ikhwan bin Aziz | E79: Dr. Abdul Aziz bin Yaacob | F79: Dr. Shah Iskandar Fahmie bin Ramlee | G79: Prof. Madya Dr. Dzulkifli bin Mukhtar | H79: Fakulti Keusahawanan dan Perniagaan | M79: DOKTOR FALSAFAH | N79: PENILAIAN CADANGAN PENYELIDIKAN (PROPOSAL DEFENSE) | O79: YBrs. Prof. Madya/Dr. | P79: YBrs. Prof. Madya/Dr. | Q79: Mesyuarat Jawatankuasa Pascasiswazah Bil.2/2025 (kali ke-55) | S79: Penilaian Cadangan Penyelidikan (Proposal Defense) | T79: Doktor Falsafah | U79: Pengurusan | V79: Wang Yajuan | W79: A23E011F | X79: An Examination of Employee Participation in Guangzhou in China | Y79: 22 Mei 2025 (Khamis) | Z79: 10.00 pagi | AA79: Platform Zoom (pautan akan dimaklumkan kemudian) | AB79: 1) Prof. Dr. Balakrishnan a/l Parasuraman (Penyelia Utama) | AC79: 2) Dr. Adi Aizat bin Yajid (Penyelia Bersama) | AE79: 1) Panel 1 - Prof. Madya Dr. Mohd Nazri bin Zakaria (Tukar) 2) Panel 1 - Dr. Hasannuddiin bin Hassan (tukar)
A80: 79 | C80: APRIL | D80: Dr. Fatihah binti Mohd | E80: Dr. Hazrina binti Hasbolah | F80: Prof. Dr. Raja Suzana binti Raja Kasim | H80: Fakulti Keusahawanan dan Perniagaan | J80: Dr. Yukhtamarani a/p Permarupan | K80: Malaysian Graduate School of Entrepreneurship and Business (MGSEB) | M80: DOKTOR FALSAFAH | N80: PENILAIAN CADANGAN PENYELIDIKAN (PROPOSAL DEFENSE) | O80: YBhg. Prof./Dr. | P80: YBhg. Prof./Dr. | Q80: Mesyuarat Jawatankuasa Pascasiswazah Bil.2/2025 (kali ke-55) | S80: Penilaian Cadangan Penyelidikan (Proposal Defense) | T80: Doktor Falsafah | U80: Peruncitan | V80: Zeng Chunlong | W80: A20E0141F | X80: The Moderating Role of Transactional Leadership Style in The Relationship between Objective and Subjective Factors and Subjective Career Success Among Academic Employee in Private Universities of Guangdong, China | Y80: 13 Mei 2025 (Selasa) | Z80: 10.00 pagi | AA80: Platform Zoom (pautan akan dimaklumkan kemudian) | AB80: 1) Prof. Dr. Roselina binti Ahmad Saufi (Penyelia Utama) | AE80: Pengerusi - Dr. Nur Izzati binti Mohamad Anuar (tukar - mengetuai Mesy. Vetting Soalan peperiksaan akhir)
A81: 80 | C81: APRIL | D81: Dr. Nur Ain Ayuni binti Sabri | E81: Dr. Amira binti Jamil | F81: Dr. Noor Raihani binti Zainol | G81: Dr. Nur Izzati binti Mohamad Anuar | H81: Fakulti Keusahawanan dan Perniagaan | M81: SARJANA KEUSAHAWANAN | N81: PENILAIAN CADANGAN PENYELIDIKAN (PROPOSAL DEFENSE) | O81: YBrs. Prof. Madya/Dr. | P81: YBrs. Prof. Madya/Dr. | Q81: Mesyuarat Jawatankuasa Pascasiswazah Bil.2/2025 (kali ke-55) | S81: Penilaian Cadangan Penyelidikan (Proposal Defense) | T81: Sarjana Keusahawanan | U81: Pengurusan | V81: Hu Peng | W81: A21D071F | X81: The Impact of School-Enterprise Co-operation on Graduates Employability in China’s Universities. | Y81: 30 April 2025 (Rabu) | Z81: 10.00 pagi | AA81: Platform Zoom (pautan akan dimaklumkan kemudian) | AB81: 1) Prof. Madya Dr. Muhamad Saufi bin Che Rusuli (Penyelia Utama) | AC81: 2) Prof. Dr. Naresh Kumar a/l Samy (Penyelia Bersama) | AE81: Pengerusi - Prof. Madya Dr. Wan Farha binti Wan Zulkiffli (tukar)
A82: 81 | C82: APRIL | D82: Dr Nurnaddia binti Nordin | E82: Dr. Muhammad Firdaus bin Zakaria | F82: Dr. Azira Hanani binti Berahim @ Ab Rahman | G82: Dr. Siti Rohana binti Mohamad | H82: Fakulti Keusahawanan dan Perniagaan | M82: DOKTOR FALSAFAH | N82: PENILAIAN CADANGAN PENYELIDIKAN (PROPOSAL DEFENSE) | O82: YBrs. Dr. | P82: YBrs. Dr. | Q82: Mesyuarat Jawatankuasa Pascasiswazah Bil.2/2025 (kali ke-55) | S82: Penilaian Cadangan Penyelidikan (Proposal Defense) | T82: Doktor Falsafah | U82: Kewangan | V82: Saiful Bahri | W82: A23E011F | X82: Decomposing Overconfidence: A Multidimensional Investigation Into the Effects of Behavioral Biases on Investment Decisions of Young Investors. | Y82: 20 Mei 2025 (Selasa) | Z82: 10.00 pagi | AA82: Platform Zoom (pautan akan dimaklumkan kemudian) | AB82: 1) Dr. Ahmad Ridhuwan bin Abdullah (Penyelia Utama) | AC82: 2) Prof. Madya Dr. Mohd Zulkifli bin Muhammad (Penyelia Bersama) | AE82: Pengerusi - Dr. Mohd Afifie bin Mohd Alwi (tukar - menghadiri prog di Machang)
A83: 82 | C83: APRIL | D83: Dr. Mohamad Hazeem bin Mohmad Sidik | E83: Dr. Lu Man Hong | F83: Prof. Madya Dr. Muhammad Ashlyzan bin Razik | G83: Dr. Nur Fadiah binti Mohd Zawawi | H83: Fakulti Keusahawanan dan Perniagaan | M83: DOKTOR FALSAFAH | N83: PENILAIAN CADANGAN PENYELIDIKAN (PROPOSAL DEFENSE) | O83: YBrs. Prof. Madya/Dr. | P83: YBrs. Prof. Madya/Dr. | Q83: Mesyuarat Jawatankuasa Pascasiswazah Bil.2/2025 (kali ke-55) | S83: Penilaian Cadangan Penyelidikan (Proposal Defense) | T83: Doktor Falsafah | U83: Pengurusan Logistik dan Operasi | V83: Adeh Rose | W83: A22E132F | X83: An Empirical Study on Factors Influencing Supply Chain Performance in The Malaysian Palm Oil Industry | Y83: 19 Mei 2025 (Isnin) | Z83: 2.30 petang | AA83: Platform Zoom (pautan akan dimaklumkan kemudian) | AB83: 1) Prof. Madya Ts. Dr. Zuraimi bin abdul Aziz (Penyelia Utama) | AC83: 2) Dr. Kasmaruddin bin Che Hussin (Penyelia Bersama) | AE83: 1) Penolong Pengerusi - Dr. Mohamad Hazeem bin Mohmad Sidik (Tukar) 2) Pengerusi - Dr. Nur Fadiah binti Mohd Zawawi (Tukar - panel 2) 3) Panel 2 - Dr. Razman Hafifi bin Redzuan (Tukar) 4) Pengerusi - Dr. Tahirah binti Abdullah (tukar)
A84: 83 | C84: APRIL | D84: Prof. Madya Dr. Muhammad Ashlyzan bin Razik | E84: Dr. Rikinorhakis bin Ridzwan | F84: Prof. Madya Dr. Muhamad Saufi bin Che Rusuli | G84: Dr. Norzalizah binti Bahari | H84: Fakulti Keusahawanan dan Perniagaan | M84: DOKTOR FALSAFAH | N84: PENILAIAN SEMULA CADANGAN PENYELIDIKAN (RE-PROPOSAL DEFENSE) | O84: YBrs. Prof. Madya/Dr. | P84: YBrs. Prof. Madya/Dr. | Q84: Mesyuarat Jawatankuasa Pascasiswazah Bil.2/2025 (kali ke-55) | S84: Penilaian Semula Cadangan Penyelidikan (re-Proposal Defense) | T84: Doktor Falsafah | U84: Pengurusan | V84: Salini Aina binti Mamat | W84: A23E043F | X84: The Impact of Big Data Analytics Capability on Cyberpreneurship Empowerment of Micro-Entrepreneurs in Kelantan, Malaysia | Y84: 26 Mei 2025 (Isnin) | Z84: 10.00 pagi | AA84: Platform Zoom (pautan akan dimaklumkan kemudian) | AB84: 1) Prof. Madya Ts. Dr. Zailani bin Abdullah (Penyelia Utama) | AC84: 2) Dr. Norhafiza binti Othman (Penyelia Bersama) | AD84: 3) Dr. Mohd Safwan bin Ghazali (Penyelia Bersama)
A85: 84 | C85: APRIL | D85: Prof. Madya Dr. Mohd Asrul Hery bin Ibrahim | E85: Dr. Mohd Ikhwan bin Aziz | F85: Prof. Madya Dr. Wan Farha binti Wan Zulkiffli | G85: Dr. Mohd Afifie bin Mohd Alwi | H85: Fakulti Keusahawanan dan Perniagaan | M85: DOKTOR FALSAFAH | N85: PENILAIAN SEMULA CADANGAN PENYELIDIKAN (RE-PROPOSAL DEFENSE) | O85: YBrs. Prof. Madya/Dr. | P85: YBrs. Prof. Madya/Dr. | Q85: Mesyuarat Jawatankuasa Pascasiswazah Bil.2/2025 (kali ke-55) | S85: Penilaian Semula Cadangan Penyelidikan (re-Proposal Defense) | T85: Doktor Falsafah | U85: Pengurusan | V85: Mahathir bin Muhamad | W85: A17E021P | X85: Exploring the Dynamics of Digital Banking Adoption in Malaysia: The Role of User Perceptions | Y85: 24 April 2025 (Khamis) | Z85: 10.00 pagi | AA85: Platform Zoom (pautan akan dimaklumkan kemudian) | AB85: 1) Prof. Dr. Mohammad bin Ismail (Penyelia Utama) | AC85: 2) Prof. Madya Dr. Mohd Nazri bin Muhayiddin (Penyelia Bersama) | AD85: 3) Dr. Ahmad Ridhuwan bin Abdullah (Penyelia Bersama)
A86: 85 | C86: APRIL | D86: Prof. Madya. Dr. Mohd Zulkifli bin Muhammad | E86: Dr. Rikinorhakis bin Ridzwan | F86: Prof. Madya Dr. Muhamad Saufi bin Che Rusuli | G86: Dr. Fatihah binti Mohd | H86: Fakulti Keusahawanan dan Perniagaan | M86: SARJANA KEUSAHAWANAN | N86: PENILAIAN CADANGAN PENYELIDIKAN (PROPOSAL DEFENSE) | O86: YBrs. Prof. Madya/Dr. | P86: YBrs. Prof. Madya/Dr. | Q86: Mesyuarat Jawatankuasa Pascasiswazah Bil.2/2025 (kali ke-55) | S86: Penilaian Cadangan Penyelidikan (Proposal Defense) | T86: Sarjana Keusahawanan | U86: Pengurusan | V86: Irekeola Annat Adebola | W86: A21D011F | X86: The Relationship Between System Quality and Information Quality on Nigerians e-Commerce Users Satisfaction and Intention to Revisit. | Y86: 27 Mei 2025 (Selasa) | Z86: 10.00 pagi | AA86: Platform Zoom (pautan akan dimaklumkan kemudian) | AB86: 1) Prof. Madya Dr. Muhammad Ashlyzan bin Razik (Penyelia Utama) | AC86: 2) Dr. Mohamad Hazeem bin Mohmad Sidik (Penyelia Bersama)
A87: 86 | C87: APRIL | D87: Dr. Nur Syakirah binti Ahmad | E87: Pn. Aimi Nadia binti Ibrahim @ Zakaria | F87: Prof. Dr. Mohammad bin Ismail | G87: Dr. Nik Syuhailah binti Nik Hussin | H87: Fakulti Keusahawanan dan Perniagaan | M87: DOKTOR FALSAFAH | N87: PRA PEPERIKSAAN LISAN (PRE VIVA VOCE) | O87: YBhg. Prof./Dr./Puan | P87: YBhg. Prof./Dr./Puan | Q87: Mesyuarat Jawatankuasa Pascasiswazah Bil.3/2025 (kali ke-56) | S87: Pra Peperiksaan Lisan (Pre Viva Voce) | T87: Doktor Falsafah | U87: Pemasaran | V87: Shen Ke | W87: A21E049F | X87: The Impact of eWOM Characteristics on Travel Intention Among Generation Z in China: Mediating by Attitude Towards Information Adoption | Y87: 21 Mei 2025 (Rabu) | Z87: 10.00 pagi | AA87: Platform Zoom (pautan akan dimaklumkan kemudian) | AB87: 1) Prof. Madya Dr. Wan Farha binti Wan Zulkiffli | AE87: Pengerusi - Dr. Norfazlirda binti Hairani (Tukar)
A88: 87 | C88: MEI | D88: Dr. Azira Hanani binti Berahim @ Ab Rahman | E88: En. Mohamed Ariff bin Abdul Rahman | F88: Prof. Madya. Dr. Mohd Zulkifli bin Muhammad | G88: Dr. Tahirah binti Abdullah | H88: Fakulti Keusahawanan dan Perniagaan | M88: SARJANA KEUSAHAWANAN | N88: PRA PEPERIKSAAN LISAN (PRE VIVA VOCE) | O88: YBrs. Prof. Madya/Dr. | P88: YBrs. Prof. Madya/Dr. | Q88: Mesyuarat Jawatankuasa Pascasiswazah Bil.3/2025 (kali ke-56) | S88: Pra Peperiksaan Lisan (Pre Viva Voce) | T88: Sarjana Keusahawanan | U88: Perakaunan | V88: Nur Athirah binti Mohd Aluwi | W88: A20D0211F | X88: Corporate Ethics Commitment to Enhance Financial Reporting Quality for Public Listed Companies in Malaysia | Y88: 19 Mei 2025 (Isnin) | Z88: 10.00 pagi | AA88: Platform Zoom (pautan akan dimaklumkan kemudian) | AB88: 1) Prof. Madya Dr. Noorul Azwin binti Md Nasir (Penyelia Utama) | AC88: 2) Prof. Dr. Mohd Nor Hakimin bin Yusof (Penyelia Bersama)
A89: 88 | C89: MEI | D89: Prof. Madya. Dr. Mohd Zulkifli bin Muhammad | E89: Dr. Razman Hafifi bin Redzuan | F89: Prof. Madya Dr. Noor Hasmini binti Abd Ghani | G89: Dr. Nik Syuhailah binti Nik Hussin | H89: Fakulti Keusahawanan dan Perniagaan | M89: DOKTOR FALSAFAH | N89: PRA PEPERIKSAAN LISAN (PRE VIVA VOCE) | O89: YBrs. Prof. Madya/Dr. | P89: YBrs. Prof. Madya/Dr. | Q89: Mesyuarat Jawatankuasa Pascasiswazah Bil.4/2025 (kali ke-57) | S89: Pra Peperiksaan Lisan (Pre Viva Voce) | T89: Doktor Falsafah | U89: Pemasaran | V89: Wu QianYing | W89: A21E055F | X89: A Study Of Consumption Intention Of The Coffee Shop In Guangzhou Area: Mediating Effects From Satisfaction | Y89: 25 Mei 2025 (Ahad) | Z89: 10.00 pagi | AA89: Platform Zoom (pautan akan dimaklumkan kemudian) | AB89: 1) Prof. Dr. Mohammad bin Ismail (Penyelia Utama) | AC89: 2) Dr. Syarizal bin Abdul Rahim (Penyeia Bersama)
A90: 89 | C90: MEI | D90: Dr. Nur Syafiqah binti A. Samad | E90: Dr. Rikinorhakis bin Ridzwan | G90: Dr. Nur Izzati binti Mohamad Anuar | H90: Fakulti Keusahawanan dan Perniagaan | J90: Prof. Dr. Naresh Kumar a/l Samy | K90: Malaysian Graduate School of Entrepreneurship and Business (MGSEB) | M90: SARJANA KEUSAHAWANAN | N90: PRA PEPERIKSAAN LISAN (PRE VIVA VOCE) | O90: YBhg. Prof./Dr. | P90: YBhg. Prof./Dr. | Q90: Mesyuarat Jawatankuasa Pascasiswazah Bil.4/2025 (kali ke-57) | S90: Pra Peperiksaan Lisan (Pre Viva Voce) | T90: Sarjana Keusahawanan | U90: Pengurusan Sumber Manusia | V90: Thiiruchelvi a/p Gunasagaran | W90: A20D077P | X90: English as a Second Language (ESL) Teachers Preparedness Towards Students Achievements | Y90: 27 Mei 2025 (Selasa) | Z90: 10.00 pagi | AA90: Platform Zoom (pautan akan dimaklumkan kemudian) | AB90: 1) Dr. P. Yukthamarani a/p Permarupan
A91: 90 | C91: JUN | D91: Dr. Syarizal bin Abdul Rahim | E91: Dr. Abdul Aziz bin Yaacob | F91: Prof. Dr. Mohd Nor Hakimin bin Yusoff | G91: Prof. Madya Dr. Wan Farha binti Wan Zulkiffli | H91: Fakulti Keusahawanan dan Perniagaan | M91: DOKTOR FALSAFAH | N91: PENILAIAN CADANGAN PENYELIDIKAN (PROPOSAL DEFENSE) | O91: YBhg. Prof./Dr. | P91: YBhg. Prof./Dr. | Q91: Mesyuarat Jawatankuasa Pascasiswazah Bil.4/2025 (kali ke-57) | S91: Penilaian Cadangan Penyelidikan (Proposal Defense) | T91: Doktor Falsafah | U91: Keusahawanan | V91: Ahmad Syakir bin Junoh @ Ismail | W91: A23E025F | X91: Relationships Between Leadership Strategies, Regulatory Focus and Entrepreneurial Behavior among Academics in Malaysian Public Higher Education Institutions | Y91: 10 Jun 2025 (Rabu) | Z91: 2.30 petang | AA91: Platform Zoom (pautan akan dimaklumkan kemudian) | AB91: 1) Prof. Dr. Naresh Kumar a/l Samy (Penyelia Utama) | AC91: 2) Dr. Mohd Ikhwan bin Aziz (Penyelia Bersama)
A92: 91 | C92: JUN | D92: Dr. Tahirah binti Abdullah | E92: Pn. Azizah binti Musa | F92: Dr. Amira binti Jamil | G92: Dr. Siti Fariha binti Muhamad | H92: Fakulti Keusahawanan dan Perniagaan | M92: DOKTOR FALSAFAH | N92: PENILAIAN CADANGAN PENYELIDIKAN (PROPOSAL DEFENSE) | O92: YBrs. Dr./Puan | P92: YBrs. Dr./Puan | Q92: Mesyuarat Jawatankuasa Pascasiswazah Bil.4/2025 (kali ke-57) | S92: Penilaian Cadangan Penyelidikan (Proposal Defense) | T92: Doktor Falsafah | U92: Perakaunan | V92: Setyo Mahanani | W92: A23E079F | X92: The Influence Of Corporate Financial Factors On Tax Aggressiveness Moderated By Corporate Governance In Indonesia | Y92: 24 Jun 2025 (Selasa) | Z92: 2.30 petang | AA92: Platform Zoom (pautan akan dimaklumkan kemudian) | AB92: 1) Prof. Madya Dr. Noorul Azwin binti Md Nasir (Penyelia Utama)
A93: 92 | C93: JUN | D93: Dr. Nur Syafiqah binti A. Samad | E93: Dr. Hazrina binti Hasbolah | F93: Dr. Syamsuriana Binti Sidek | G93: Dr. Shah Iskandar Fahmie bin Ramlee | H93: Fakulti Keusahawanan dan Perniagaan | M93: DOKTOR FALSAFAH | N93: PENILAIAN CADANGAN PENYELIDIKAN (PROPOSAL DEFENSE) | O93: YBrs. Dr. | P93: YBrs. Dr. | Q93: Mesyuarat Jawatankuasa Pascasiswazah Bil.4/2025 (kali ke-57) | S93: Penilaian Cadangan Penyelidikan (Proposal Defense) | T93: Doktor Falsafah | U93: Pengurusan | V93: Zhou Chunmei | W93: I20E0223F | X93: Entrepreneurial Intention of Urban Youth in China | Y93: 22 Jun 2025 (Ahad) | Z93: 10.00 pagi | AA93: Platform Zoom (pautan akan dimaklumkan kemudian) | AB93: 1) Dr. Norzalizah binti Bahari (Penyelia Utama) | AC93: 2) Dr. Hasannuddiin bin Hassan (Penyelia Bersama)
A94: 93 | C94: JUN | D94: Dr. Ahmad Ridhuwan Bin Abdullah | E94: Dr. Nurul Muna binti Mohamad | F94: Prof. Madya. Dr. Mohd Zulkifli bin Muhammad | G94: Dr. Nurhaiza binti Nordin | H94: Fakulti Keusahawanan dan Perniagaan | M94: DOKTOR FALSAFAH | N94: PENILAIAN CADANGAN PENYELIDIKAN (PROPOSAL DEFENSE) | O94: YBrs. Prof. Madya/Dr. | P94: YBrs. Prof. Madya/Dr. | Q94: Mesyuarat Jawatankuasa Pascasiswazah Bil.4/2025 (kali ke-57) | S94: Penilaian Cadangan Penyelidikan (Proposal Defense) | T94: Doktor Falsafah | U94: Perbankan dan Kewangan Islam | V94: Wan Yusrol Rizal bin Wan Yusof | W94: A23E2785P | X94: Investigating the Nexus of Sustainability and Performance of Islamic Banks in Asean-5 Countries | Y94: 29 Jun 2025 (Ahad) | Z94: 2.30 petang | AA94: Platform Zoom (pautan akan dimaklumkan kemudian) | AB94: 1) Prof. Madya Dr. Hazriah binti Hasan (Penyelia Utama) | AC94: 2) Dr. Mardhiah binti Kamaruddin (Penyelia Bersama) | AD94: 3) Prof. Dr. Baharom bin Abdul Hamid (Penyelia Luar)
A95: 94 | C95: JUN | D95: Prof. Madya Dr. Mohd Asrul Hery bin Ibrahim | E95: Dr. Nur Syakirah binti Ahmad | F95: Prof. Madya Dr. Mohd Nazri bin Zakaria | G95: Dr. Shah Iskandar Fahmie bin Ramlee | H95: Fakulti Keusahawanan dan Perniagaan | M95: DOKTOR FALSAFAH | N95: PENILAIAN CADANGAN PENYELIDIKAN (PROPOSAL DEFENSE) | O95: YBrs. Prof. Madya/Dr. | P95: YBrs. Prof. Madya/Dr. | Q95: Mesyuarat Jawatankuasa Pascasiswazah Bil.4/2025 (kali ke-57) | S95: Penilaian Cadangan Penyelidikan (Proposal Defense) | T95: Doktor Falsafah | U95: Pengurusan | V95: Muhamad Afifizuhdi bin Muhamad Sukri | W95: A22E049F | X95: The Mediating Role of Emotional Labor on Relationships Between Workplace Incivility and Emotional Exhaustion Among Quality Control Managers in Malaysia | Y95: 25 Jun 2025 (Rabu) | Z95: 10.00 pagi | AA95: Platform Zoom (pautan akan dimaklumkan kemudian) | AB95: 1) Prof. Dr. Naresh Kumar a/l Samy (Penyelia Utama)
A96: 95 | C96: JUN | D96: Prof. Madya Dr. Hazriah binti Hasan | E96: Dr. Muhammad Firdaus bin Zakaria | F96: Prof. Madya Ts. Dr. Zuraimi bin Abdul Aziz | G96: Dr. Mohamad Hazeem bin Mohmad Sidik | H96: Fakulti Keusahawanan dan Perniagaan | M96: DOKTOR FALSAFAH | N96: PENILAIAN CADANGAN PENYELIDIKAN (PROPOSAL DEFENSE) | O96: YBrs. Prof. Madya/Dr. | P96: YBrs. Prof. Madya/Dr. | Q96: Mesyuarat Jawatankuasa Pascasiswazah Bil.4/2025 (kali ke-57) | S96: Penilaian Cadangan Penyelidikan (Proposal Defense) | T96: Doktor Falsafah | U96: Pengurusan Logistik dan Operasi | V96: Abdul Ganiw Hussein | W96: A24E3681F | X96: The Role of Green Supply Chain Management and Government Regulations | Y96: 1 Julai 2025 (Rabu) | Z96: 10.00 pagi | AA96: Platform Zoom (pautan akan dimaklumkan kemudian) | AB96: 1) Prof. Madya Dr. Muhammad Ashlyzan bin Razik (Penyelia Utama) | AC96: 2) Dr. Kasmaruddin bin Che Hussin (Penyelia Bersama)
A97: 96 | C97: JUN | D97: Dr. Norfazlirda binti Hairani | E97: Dr. Norhafifah binti Samsudin | F97: Prof. Madya Ts. Dr. Zuraimi bin Abdul Aziz | G97: Dr. Nur Fadiah binti Mohd Zawawi | H97: Fakulti Keusahawanan dan Perniagaan | M97: DOKTOR FALSAFAH | N97: PENILAIAN CADANGAN PENYELIDIKAN (PROPOSAL DEFENSE) | O97: YBrs. Prof. Madya/Dr. | P97: YBrs. Prof. Madya/Dr. | Q97: Mesyuarat Jawatankuasa Pascasiswazah Bil.4/2025 (kali ke-57) | S97: Penilaian Cadangan Penyelidikan (Proposal Defense) | T97: Doktor Falsafah | U97: Pengurusan Logistik dan Operasi | V97: Adam Osman Oscar | W97: A24E2832F | X97: Green Public Procurement in Ghana: An Analysis of Environmental Sustainability in Public Procurement | Y97: 13 Julai 2025 (Ahad) | Z97: 10.00 pagi | AA97: Platform Zoom (pautan akan dimaklumkan kemudian) | AB97: 1) Prof. Madya Dr. Muhammad Ashlyzan bin Razik (Penyelia Utama) | AC97: 2) Dr. Kasmaruddin bin Che Hussin (Penyelia Bersama) | AE97: Pengerusi - Prof. Madya Dr. Muhamad Saufi bin Che Rusuli (Tukar - Menyantuni delegasi Gabenor Thailand di UMK Jeli)
A98: 97 | C98: JUN | D98: Dr. Nurhaiza binti Nordin | E98: En. Syed Azlan Aljaffree bin Syed Khadzil | F98: Dr. Siti Fariha binti Muhamad | G98: Dr. Nor Asma Binti Ahmad | H98: Fakulti Keusahawanan dan Perniagaan | M98: DOKTOR FALSAFAH | N98: PENILAIAN CADANGAN PENYELIDIKAN (PROPOSAL DEFENSE) | O98: YBrs. Prof. Madya/Dr. | P98: YBrs. Prof. Madya/Dr. | Q98: Mesyuarat Jawatankuasa Pascasiswazah Bil.4/2025 (kali ke-57) | S98: Penilaian Cadangan Penyelidikan (Proposal Defense) | T98: Doktor Falsafah | U98: Kewangan | V98: Yusnita Octafilia Theresia A Yesu Infante | W98: A22E167F | X98: The Impact of Corporate Governance and ESG Disclosure on The Performance of Indonesia-Listed Firms | Y98: 8 Julai 2025 (Selasa) | Z98: 10.00 pagi | AA98: Platform Zoom (pautan akan dimaklumkan kemudian) | AB98: 1) Dr. Zaminor binti Zamzamir @ Zamzamin (Penyelia Utama) | AC98: 2) Dr. Ahmad Ridhuwan Bin Abdullah (Penyelia Bersama) | AE98: Pengerusi - Prof. Madya. Dr. Mohd Zulkifli bin Muhammad (tukar - pembedahan mata)
A99: 98 | C99: JUN | D99: Dr. Abdul Aziz bin Yaacob | E99: Dr. Muhammad Zulfaris bin Mohd Salleh | F99: Prof. Madya Dr. Hazriah binti Hasan | H99: Fakulti Keusahawanan dan Perniagaan | J99: Prof. Madya Dr. Mohd Zain bin Mubarak | K99: Fakulti Pengajian Bahasa Dan Pembangunan Insan | M99: DOKTOR FALSAFAH | N99: PRA PEPERIKSAAN LISAN (PRE VIVA VOCE) | O99: YBrs. Prof. Madya/Dr. | P99: YBrs. Prof. Madya/Dr. | Q99: Mesyuarat Jawatankuasa Pascasiswazah Bil.4/2025 (kali ke-57) | S99: Pra Peperiksaan Lisan (Pre Viva Voce) | T99: Doktor Falsafah | U99: Keusahawanan | V99: Khaulah binti Hilaluddin | W99: A20E0163F | X99: Teori Keusahawanan Penciptaan Perniagaan Baharu Menurut Perspektif Islam Berdasarkan Al-Kutub Al-Tis'ah | Y99: 26 Jun 2025 (Khamis) | Z99: 10.00 pagi | AA99: Platform Zoom (pautan akan dimaklumkan kemudian) | AB99: 1) Prof. Madya Dr. Mohd Nazri bin Muhayiddin (Penyelia Utama) | AC99: 2) Prof. Madya. Dr. Mohd Zulkifli bin Muhammad (Penyelia Bersama) | AD99: 3) Prof. Madya Dr. Anis Amira binti Ab Rahman (Penyelia Bersama) | AE99: Pengerusi - Prof. Madya Dr. Azwan bin Abdullah (tukar - program lapangan di Tumpat utk lawatan pemantauan geran TRGS bersama UMS) Pengerusi - Dr. Siti Rohana binti Mohamad (Tukar)
A100: 99 | C100: JUN | D100: Dr. Kasmaruddin bin Che Hussin | E100: Dr. Muhammad Firdaus bin Zakaria | F100: Prof. Dr. Mohammad bin Ismail | G100: Prof. Madya Dr. Wan Farha binti Wan Zulkiffli | H100: Fakulti Keusahawanan dan Perniagaan | M100: DOKTOR FALSAFAH | N100: PRA PEPERIKSAAN LISAN (PRE VIVA VOCE) | O100: YBhg. Prof. /Prof. Madya/Dr. | P100: YBhg. Prof. /Prof. Madya/Dr. | Q100: Mesyuarat Jawatankuasa Pascasiswazah Bil.5/2025 (kali ke-58) | S100: Pra Peperiksaan Lisan (Pre Viva Voce) | T100: Doktor Falsafah | U100: Peruncitan | V100: Aimi Nadia binti Ibrahim @ Zakaria | W100: A19E001F | X100: Brand Experience, Brand Trust and Brand Love Toward Brand Loyalty in Malaysia: The Context of Private Label Brands | Y100: 16 Jun 2025 (Isnin) | Z100: 09.00 pagi | AA100: Platform Zoom (pautan akan dimaklumkan kemudian) | AB100: 1) Prof. Madya Dr. Noor Hasmini Hj Abd Ghani (Penyelia Utama)
...

Sheet KEKERAPAN 
A1: KEKERAPAN PENSYARAH YANG TERLIBAT DENGAN PENILAIAN CADANGAN PENYELIDIKAN (PD) DAN PRA PEPERIKSAAN LISAN (CD)
A3: Bil | B3: Pensyarah | C3: TAHUN 2024 | H3: TAHUN 2025
C4: Pengerusi | D4: Penolong Pengerusi | E4: panel 1 | F4: panel 2 | G4: Jumlah Kekerapan | H4: Pengerusi | I4: Penolong Pengerusi | J4: panel 1 | K4: panel 2 | L4: Jumlah Kekerapan
A5: 1 | B5: Prof. Dr. Raja Suzana binti Raja Kasim | C5: =COUNTIF(DATA_SURAT_PELANTIKAN!$D$2:$D$56,B5) -> 0 | D5: =COUNTIF(DATA_SURAT_PELANTIKAN!$E$2:$E$56,B5) -> 0 | E5: =COUNTIF(DATA_SURAT_PELANTIKAN!$F$2:$F$56,B5) -> 2 | F5: =COUNTIF(DATA_SURAT_PELANTIKAN!$G$2:$G$56,B5) -> 0 | G5: =SUM(C5:F5) -> 2 | H5: =COUNTIF(DATA_SURAT_PELANTIKAN!$D$57:$D$150,B5) -> 0 | I5: =COUNTIF(DATA_SURAT_PELANTIKAN!$E$57:$E$150,B5) -> 0 | J5: =COUNTIF(DATA_SURAT_PELANTIKAN!$F$57:$F$150,B5) -> 3 | K5: =COUNTIF(DATA_SURAT_PELANTIKAN!$G$57:$G$150,B5) -> 0 | L5: =SUM(H5:K5) -> 3
A6: 2 | B6: Prof. Dr. Mohd Rafi bin Yaacob | C6: =COUNTIF(DATA_SURAT_PELANTIKAN!$D$2:$D$56,B6) -> 0 | D6: =COUNTIF(DATA_SURAT_PELANTIKAN!$E$2:$E$56,B6) -> 0 | E6: =COUNTIF(DATA_SURAT_PELANTIKAN!$F$2:$F$56,B6) -> 8 | F6: =COUNTIF(DATA_SURAT_PELANTIKAN!$G$2:$G$56,B6) -> 2 | G6: =SUM(C6:F6) -> 10 | H6: =COUNTIF(DATA_SURAT_PELANTIKAN!$D$57:$D$150,B6) -> 0 | I6: =COUNTIF(DATA_SURAT_PELANTIKAN!$E$57:$E$150,B6) -> 0 | J6: =COUNTIF(DATA_SURAT_PELANTIKAN!$F$57:$F$150,B6) -> 0 | K6: =COUNTIF(DATA_SURAT_PELANTIKAN!$G$57:$G$150,B6) -> 0 | L6: =SUM(H6:K6) -> 0
A7: 3 | B7: Prof. Dr. Balakrishnan A/L Parasuraman | C7: =COUNTIF(DATA_SURAT_PELANTIKAN!$D$2:$D$56,B7) -> 3 | D7: =COUNTIF(DATA_SURAT_PELANTIKAN!$E$2:$E$56,B7) -> 0 | E7: =COUNTIF(DATA_SURAT_PELANTIKAN!$F$2:$F$56,B7) -> 1 | F7: =COUNTIF(DATA_SURAT_PELANTIKAN!$G$2:$G$56,B7) -> 0 | G7: =SUM(C7:F7) -> 4 | H7: =COUNTIF(DATA_SURAT_PELANTIKAN!$D$57:$D$150,B7) -> 0 | I7: =COUNTIF(DATA_SURAT_PELANTIKAN!$E$57:$E$150,B7) -> 0 | J7: =COUNTIF(DATA_SURAT_PELANTIKAN!$F$57:$F$150,B7) -> 3 | K7: =COUNTIF(DATA_SURAT_PELANTIKAN!$G$57:$G$150,B7) -> 0 | L7: =SUM(H7:K7) -> 3
A8: 4 | B8: Prof. Dr. Mohd Nor Hakimin bin Yusoff | C8: =COUNTIF(DATA_SURAT_PELANTIKAN!$D$2:$D$56,B8) -> 0 | D8: =COUNTIF(DATA_SURAT_PELANTIKAN!$E$2:$E$56,B8) -> 0 | E8: =COUNTIF(DATA_SURAT_PELANTIKAN!$F$2:$F$56,B8) -> 4 | F8: =COUNTIF(DATA_SURAT_PELANTIKAN!$G$2:$G$56,B8) -> 1 | G8: =SUM(C8:F8) -> 5 | H8: =COUNTIF(DATA_SURAT_PELANTIKAN!$D$57:$D$150,B8) -> 0 | I8: =COUNTIF(DATA_SURAT_PELANTIKAN!$E$57:$E$150,B8) -> 0 | J8: =COUNTIF(DATA_SURAT_PELANTIKAN!$F$57:$F$150,B8) -> 5 | K8: =COUNTIF(DATA_SURAT_PELANTIKAN!$G$57:$G$150,B8) -> 1 | L8: =SUM(H8:K8) -> 6
A9: 5 | B9: Prof. Dr. Mohammad bin Ismail | C9: =COUNTIF(DATA_SURAT_PELANTIKAN!$D$2:$D$56,B9) -> 0 | D9: =COUNTIF(DATA_SURAT_PELANTIKAN!$E$2:$E$56,B9) -> 0 | E9: =COUNTIF(DATA_SURAT_PELANTIKAN!$F$2:$F$56,B9) -> 0 | F9: =COUNTIF(DATA_SURAT_PELANTIKAN!$G$2:$G$56,B9) -> 0 | G9: =SUM(C9:F9) -> 0 | H9: =COUNTIF(DATA_SURAT_PELANTIKAN!$D$57:$D$150,B9) -> 0 | I9: =COUNTIF(DATA_SURAT_PELANTIKAN!$E$57:$E$150,B9) -> 0 | J9: =COUNTIF(DATA_SURAT_PELANTIKAN!$F$57:$F$150,B9) -> 0 | K9: =COUNTIF(DATA_SURAT_PELANTIKAN!$G$57:$G$150,B9) -> 0 | L9: =SUM(H9:K9) -> 0
A10: 6 | B10: Prof. Madya Dr. Dzulkifli bin Mukhtar | C10: =COUNTIF(DATA_SURAT_PELANTIKAN!$D$2:$D$56,B10) -> 2 | D10: =COUNTIF(DATA_SURAT_PELANTIKAN!$E$2:$E$56,B10) -> 0 | E10: =COUNTIF(DATA_SURAT_PELANTIKAN!$F$2:$F$56,B10) -> 5 | F10: =COUNTIF(DATA_SURAT_PELANTIKAN!$G$2:$G$56,B10) -> 2 | G10: =SUM(C10:F10) -> 9 | H10: =COUNTIF(DATA_SURAT_PELANTIKAN!$D$57:$D$150,B10) -> 0 | I10: =COUNTIF(DATA_SURAT_PELANTIKAN!$E$57:$E$150,B10) -> 0 | J10: =COUNTIF(DATA_SURAT_PELANTIKAN!$F$57:$F$150,B10) -> 5 | K10: =COUNTIF(DATA_SURAT_PELANTIKAN!$G$57:$G$150,B10) -> 1 | L10: =SUM(H10:K10) -> 6
A11: 7 | B11: Prof. Madya. Dr. Mohd Zulkifli bin Muhammad | C11: =COUNTIF(DATA_SURAT_PELANTIKAN!$D$2:$D$56,B11) -> 4 | D11: =COUNTIF(DATA_SURAT_PELANTIKAN!$E$2:$E$56,B11) -> 0 | E11: =COUNTIF(DATA_SURAT_PELANTIKAN!$F$2:$F$56,B11) -> 0 | F11: =COUNTIF(DATA_SURAT_PELANTIKAN!$G$2:$G$56,B11) -> 0 | G11: =SUM(C11:F11) -> 4 | H11: =COUNTIF(DATA_SURAT_PELANTIKAN!$D$57:$D$150,B11) -> 5 | I11: =COUNTIF(DATA_SURAT_PELANTIKAN!$E$57:$E$150,B11) -> 0 | J11: =COUNTIF(DATA_SURAT_PELANTIKAN!$F$57:$F$150,B11) -> 5 | K11: =COUNTIF(DATA_SURAT_PELANTIKAN!$G$57:$G$150,B11) -> 1 | L11: =SUM(H11:K11) -> 11
A12: 8 | B12: Prof. Madya Dr. Mohd Nazri bin Zakaria | C12: =COUNTIF(DATA_SURAT_PELANTIKAN!$D$2:$D$56,B12) -> 2 | D12: =COUNTIF(DATA_SURAT_PELANTIKAN!$E$2:$E$56,B12) -> 0 | E12: =COUNTIF(DATA_SURAT_PELANTIKAN!$F$2:$F$56,B12) -> 2 | F12: =COUNTIF(DATA_SURAT_PELANTIKAN!$G$2:$G$56,B12) -> 2 | G12: =SUM(C12:F12) -> 6 | H12: =COUNTIF(DATA_SURAT_PELANTIKAN!$D$57:$D$150,B12) -> 2 | I12: =COUNTIF(DATA_SURAT_PELANTIKAN!$E$57:$E$150,B12) -> 0 | J12: =COUNTIF(DATA_SURAT_PELANTIKAN!$F$57:$F$150,B12) -> 4 | K12: =COUNTIF(DATA_SURAT_PELANTIKAN!$G$57:$G$150,B12) -> 0 | L12: =SUM(H12:K12) -> 6
A13: 9 | B13: Prof. Madya Dr. Wan Farha binti Wan Zulkiffli | C13: =COUNTIF(DATA_SURAT_PELANTIKAN!$D$2:$D$56,B13) -> 0 | D13: =COUNTIF(DATA_SURAT_PELANTIKAN!$E$2:$E$56,B13) -> 0 | E13: =COUNTIF(DATA_SURAT_PELANTIKAN!$F$2:$F$56,B13) -> 3 | F13: =COUNTIF(DATA_SURAT_PELANTIKAN!$G$2:$G$56,B13) -> 1 | G13: =SUM(C13:F13) -> 4 | H13: =COUNTIF(DATA_SURAT_PELANTIKAN!$D$57:$D$150,B13) -> 0 | I13: =COUNTIF(DATA_SURAT_PELANTIKAN!$E$57:$E$150,B13) -> 0 | J13: =COUNTIF(DATA_SURAT_PELANTIKAN!$F$57:$F$150,B13) -> 2 | K13: =COUNTIF(DATA_SURAT_PELANTIKAN!$G$57:$G$150,B13) -> 4 | L13: =SUM(H13:K13) -> 6
A14: 10 | B14: Prof. Madya Dr. Muhamad Saufi bin Che Rusuli | C14: =COUNTIF(DATA_SURAT_PELANTIKAN!$D$2:$D$56,B14) -> 1 | D14: =COUNTIF(DATA_SURAT_PELANTIKAN!$E$2:$E$56,B14) -> 0 | E14: =COUNTIF(DATA_SURAT_PELANTIKAN!$F$2:$F$56,B14) -> 2 | F14: =COUNTIF(DATA_SURAT_PELANTIKAN!$G$2:$G$56,B14) -> 1 | G14: =SUM(C14:F14) -> 4 | H14: =COUNTIF(DATA_SURAT_PELANTIKAN!$D$57:$D$150,B14) -> 1 | I14: =COUNTIF(DATA_SURAT_PELANTIKAN!$E$57:$E$150,B14) -> 0 | J14: =COUNTIF(DATA_SURAT_PELANTIKAN!$F$57:$F$150,B14) -> 3 | K14: =COUNTIF(DATA_SURAT_PELANTIKAN!$G$57:$G$150,B14) -> 0 | L14: =SUM(H14:K14) -> 4
A15: 11 | B15: Prof. Madya Dr. Noorshella Binti Che Nawi | C15: =COUNTIF(DATA_SURAT_PELANTIKAN!$D$2:$D$56,B15) -> 0 | D15: =COUNTIF(DATA_SURAT_PELANTIKAN!$E$2:$E$56,B15) -> 0 | E15: =COUNTIF(DATA_SURAT_PELANTIKAN!$F$2:$F$56,B15) -> 1 | F15: =COUNTIF(DATA_SURAT_PELANTIKAN!$G$2:$G$56,B15) -> 1 | G15: =SUM(C15:F15) -> 2 | H15: =COUNTIF(DATA_SURAT_PELANTIKAN!$D$57:$D$150,B15) -> 0 | I15: =COUNTIF(DATA_SURAT_PELANTIKAN!$E$57:$E$150,B15) -> 0 | J15: =COUNTIF(DATA_SURAT_PELANTIKAN!$F$57:$F$150,B15) -> 1 | K15: =COUNTIF(DATA_SURAT_PELANTIKAN!$G$57:$G$150,B15) -> 0 | L15: =SUM(H15:K15) -> 1
A16: 12 | B16: Prof. Madya Ts. Dr. Zuraimi bin Abdul Aziz | C16: =COUNTIF(DATA_SURAT_PELANTIKAN!$D$2:$D$56,B16) -> 0 | D16: =COUNTIF(DATA_SURAT_PELANTIKAN!$E$2:$E$56,B16) -> 0 | E16: =COUNTIF(DATA_SURAT_PELANTIKAN!$F$2:$F$56,B16) -> 0 | F16: =COUNTIF(DATA_SURAT_PELANTIKAN!$G$2:$G$56,B16) -> 2 | G16: =SUM(C16:F16) -> 2 | H16: =COUNTIF(DATA_SURAT_PELANTIKAN!$D$57:$D$150,B16) -> 0 | I16: =COUNTIF(DATA_SURAT_PELANTIKAN!$E$57:$E$150,B16) -> 0 | J16: =COUNTIF(DATA_SURAT_PELANTIKAN!$F$57:$F$150,B16) -> 2 | K16: =COUNTIF(DATA_SURAT_PELANTIKAN!$G$57:$G$150,B16) -> 0 | L16: =SUM(H16:K16) -> 2
... A85: 81 | B85: Dr. Nurul Fadzlyn binti Enche Nadzmy | C85: =COUNTIF(DATA_SURAT_PELANTIKAN!$D$2:$D$56,B85) -> 0 | D85: =COUNTIF(DATA_SURAT_PELANTIKAN!$E$2:$E$56,B85) -> 0 | E85: =COUNTIF(DATA_SURAT_PELANTIKAN!$F$2:$F$56,B85) -> 0 | F85: =COUNTIF(DATA_SURAT_PELANTIKAN!$G$2:$G$56,B85) -> 0 | G85: =SUM(C85:F85) -> 0 | H85: =COUNTIF(DATA_SURAT_PELANTIKAN!$D$57:$D$150,B85) -> 0 | I85: =COUNTIF(DATA_SURAT_PELANTIKAN!$E$57:$E$150,B85) -> 2 | J85: =COUNTIF(DATA_SURAT_PELANTIKAN!$F$57:$F$150,B85) -> 0 | K85: =COUNTIF(DATA_SURAT_PELANTIKAN!$G$57:$G$150,B85) -> 0 | L85: =SUM(H85:K85) -> 2
A86: 82 | B86: Dr Nurnaddia binti Nordin | C86: =COUNTIF(DATA_SURAT_PELANTIKAN!$D$2:$D$56,B86) -> 0 | D86: =COUNTIF(DATA_SURAT_PELANTIKAN!$E$2:$E$56,B86) -> 0 | E86: =COUNTIF(DATA_SURAT_PELANTIKAN!$F$2:$F$56,B86) -> 0 | F86: =COUNTIF(DATA_SURAT_PELANTIKAN!$G$2:$G$56,B86) -> 0 | G86: =SUM(C86:F86) -> 0 | H86: =COUNTIF(DATA_SURAT_PELANTIKAN!$D$57:$D$150,B86) -> 1 | I86: =COUNTIF(DATA_SURAT_PELANTIKAN!$E$57:$E$150,'KEKERAPAN '!B86) -> 1 | J86: =COUNTIF(DATA_SURAT_PELANTIKAN!$F$57:$F$150,B86) -> 0 | K86: =COUNTIF(DATA_SURAT_PELANTIKAN!$G$57:$G$150,B86) -> 0 | L86: =SUM(H86:K86) -> 2
A87: 83 | B87: Dr. Razman Hafifi bin Redzuan | C87: =COUNTIF(DATA_SURAT_PELANTIKAN!$D$2:$D$56,B87) -> 0 | D87: =COUNTIF(DATA_SURAT_PELANTIKAN!$E$2:$E$56,B87) -> 0 | E87: =COUNTIF(DATA_SURAT_PELANTIKAN!$F$2:$F$56,B87) -> 0 | F87: =COUNTIF(DATA_SURAT_PELANTIKAN!$G$2:$G$56,B87) -> 0 | G87: =SUM(C87:F87) -> 0 | H87: =COUNTIF(DATA_SURAT_PELANTIKAN!$D$57:$D$150,B87) -> 0 | I87: =COUNTIF(DATA_SURAT_PELANTIKAN!$E$57:$E$150,B87) -> 1 | J87: =COUNTIF(DATA_SURAT_PELANTIKAN!$F$57:$F$150,B87) -> 0 | K87: =COUNTIF(DATA_SURAT_PELANTIKAN!$G$57:$G$150,B87) -> 0 | L87: =SUM(H87:K87) -> 1
A88: 84 | B88: Dr. Nurhaiza binti Nordin | C88: =COUNTIF(DATA_SURAT_PELANTIKAN!$D$2:$D$56,B88) -> 0 | D88: =COUNTIF(DATA_SURAT_PELANTIKAN!$E$2:$E$56,B88) -> 0 | E88: =COUNTIF(DATA_SURAT_PELANTIKAN!$F$2:$F$56,B88) -> 0 | F88: =COUNTIF(DATA_SURAT_PELANTIKAN!$G$2:$G$56,B88) -> 0 | G88: =SUM(C88:F88) -> 0 | H88: =COUNTIF(DATA_SURAT_PELANTIKAN!$D$57:$D$150,B88) -> 1 | I88: =COUNTIF(DATA_SURAT_PELANTIKAN!$E$57:$E$150,B88) -> 1 | J88: =COUNTIF(DATA_SURAT_PELANTIKAN!$F$57:$F$150,B88) -> 0 | K88: =COUNTIF(DATA_SURAT_PELANTIKAN!$G$57:$G$150,B88) -> 2 | L88: =SUM(H88:K88) -> 4
A89: 85 | B89: Dr. Fatihah binti Mohd | C89: =COUNTIF(DATA_SURAT_PELANTIKAN!$D$2:$D$56,B89) -> 0 | D89: =COUNTIF(DATA_SURAT_PELANTIKAN!$E$2:$E$56,B89) -> 0 | E89: =COUNTIF(DATA_SURAT_PELANTIKAN!$F$2:$F$56,B89) -> 0 | F89: =COUNTIF(DATA_SURAT_PELANTIKAN!$G$2:$G$56,B89) -> 0 | G89: =SUM(C89:F89) -> 0 | H89: =COUNTIF(DATA_SURAT_PELANTIKAN!$D$57:$D$150,B89) -> 1 | I89: =COUNTIF(DATA_SURAT_PELANTIKAN!$E$57:$E$150,B89) -> 0 | J89: =COUNTIF(DATA_SURAT_PELANTIKAN!$F$57:$F$150,B89) -> 0 | K89: =COUNTIF(DATA_SURAT_PELANTIKAN!$G$57:$G$150,B89) -> 1 | L89: =SUM(H89:K89) -> 2
A90: 86 | B90: En. Mohammad Nizamuddin bin Abdul Rahim | C90: =COUNTIF(DATA_SURAT_PELANTIKAN!$D$2:$D$56,B90) -> 0 | D90: =COUNTIF(DATA_SURAT_PELANTIKAN!$E$2:$E$56,B90) -> 0 | E90: =COUNTIF(DATA_SURAT_PELANTIKAN!$F$2:$F$56,B90) -> 0 | F90: =COUNTIF(DATA_SURAT_PELANTIKAN!$G$2:$G$56,B90) -> 0 | G90: =SUM(C90:F90) -> 0 | H90: =COUNTIF(DATA_SURAT_PELANTIKAN!$D$57:$D$150,B90) -> 0 | I90: =COUNTIF(DATA_SURAT_PELANTIKAN!$E$57:$E$150,B90) -> 1 | J90: =COUNTIF(DATA_SURAT_PELANTIKAN!$F$57:$F$150,B90) -> 0 | K90: =COUNTIF(DATA_SURAT_PELANTIKAN!$G$57:$G$150,B90) -> 0 | L90: =SUM(H90:K90) -> 1
A91: 87 | B91: Dr. Farah Hanan binti Muhamad | C91: =COUNTIF(DATA_SURAT_PELANTIKAN!$D$2:$D$56,B91) -> 0 | D91: =COUNTIF(DATA_SURAT_PELANTIKAN!$E$2:$E$56,B91) -> 0 | E91: =COUNTIF(DATA_SURAT_PELANTIKAN!$F$2:$F$56,B91) -> 0 | F91: =COUNTIF(DATA_SURAT_PELANTIKAN!$G$2:$G$56,B91) -> 0 | G91: =SUM(C91:F91) -> 0 | H91: =COUNTIF(DATA_SURAT_PELANTIKAN!$D$57:$D$150,B91) -> 0 | I91: =COUNTIF(DATA_SURAT_PELANTIKAN!$E$57:$E$150,B91) -> 2 | J91: =COUNTIF(DATA_SURAT_PELANTIKAN!$F$57:$F$150,B91) -> 0 | K91: =COUNTIF(DATA_SURAT_PELANTIKAN!$G$57:$G$150,B91) -> 0 | L91: =SUM(H91:K91) -> 2
A92: 88 | B92: Dr. Mardhiah binti Kamaruddin | C92: =COUNTIF(DATA_SURAT_PELANTIKAN!$D$2:$D$56,B92) -> 0 | D92: =COUNTIF(DATA_SURAT_PELANTIKAN!$E$2:$E$56,B92) -> 0 | E92: =COUNTIF(DATA_SURAT_PELANTIKAN!$F$2:$F$56,B92) -> 0 | F92: =COUNTIF(DATA_SURAT_PELANTIKAN!$G$2:$G$56,B92) -> 0 | G92: =SUM(C92:F92) -> 0 | H92: =COUNTIF(DATA_SURAT_PELANTIKAN!$D$57:$D$150,B92) -> 0 | I92: =COUNTIF(DATA_SURAT_PELANTIKAN!$E$57:$E$150,B92) -> 0 | J92: =COUNTIF(DATA_SURAT_PELANTIKAN!$F$57:$F$150,B92) -> 0 | K92: =COUNTIF(DATA_SURAT_PELANTIKAN!$G$57:$G$150,B92) -> 1 | L92: =SUM(H92:K92) -> 1
A93: 89 | B93: Dr. Siti Amaliya binti Mohd Radyi | C93: =COUNTIF(DATA_SURAT_PELANTIKAN!$D$2:$D$56,B93) -> 0 | D93: =COUNTIF(DATA_SURAT_PELANTIKAN!$E$2:$E$56,B93) -> 0 | E93: =COUNTIF(DATA_SURAT_PELANTIKAN!$F$2:$F$56,B93) -> 0 | F93: =COUNTIF(DATA_SURAT_PELANTIKAN!$G$2:$G$56,B93) -> 0 | G93: =SUM(C93:F93) -> 0 | H93: =COUNTIF(DATA_SURAT_PELANTIKAN!$D$57:$D$150,B93) -> 0 | I93: =COUNTIF(DATA_SURAT_PELANTIKAN!$E$57:$E$150,B93) -> 1 | J93: =COUNTIF(DATA_SURAT_PELANTIKAN!$F$57:$F$150,B93) -> 0 | K93: =COUNTIF(DATA_SURAT_PELANTIKAN!$G$57:$G$150,B93) -> 0 | L93: =SUM(H93:K93) -> 1
A94: 90 | B94: Dr. Nur A’mira binti Mohd Yaziz | C94: =COUNTIF(DATA_SURAT_PELANTIKAN!$D$2:$D$56,B94) -> 0 | D94: =COUNTIF(DATA_SURAT_PELANTIKAN!$E$2:$E$56,B94) -> 0 | E94: =COUNTIF(DATA_SURAT_PELANTIKAN!$F$2:$F$56,B94) -> 0 | F94: =COUNTIF(DATA_SURAT_PELANTIKAN!$G$2:$G$56,B94) -> 0 | G94: =SUM(C94:F94) -> 0 | H94: =COUNTIF(DATA_SURAT_PELANTIKAN!$D$57:$D$150,B94) -> 0 | I94: =COUNTIF(DATA_SURAT_PELANTIKAN!$E$57:$E$150,B94) -> 1 | J94: =COUNTIF(DATA_SURAT_PELANTIKAN!$F$57:$F$150,B94) -> 0 | K94: =COUNTIF(DATA_SURAT_PELANTIKAN!$G$57:$G$150,B94) -> 0 | L94: =SUM(H94:K94) -> 1
A95: 91 | B95: Dr. Muhammad Pirdaus bin Yusoh | C95: =COUNTIF(DATA_SURAT_PELANTIKAN!$D$2:$D$56,B95) -> 0 | D95: =COUNTIF(DATA_SURAT_PELANTIKAN!$E$2:$E$56,B95) -> 0 | E95: =COUNTIF(DATA_SURAT_PELANTIKAN!$F$2:$F$56,B95) -> 0 | F95: =COUNTIF(DATA_SURAT_PELANTIKAN!$G$2:$G$56,B95) -> 0 | G95: =SUM(C95:F95) -> 0 | H95: =COUNTIF(DATA_SURAT_PELANTIKAN!$D$57:$D$150,B95) -> 0 | I95: =COUNTIF(DATA_SURAT_PELANTIKAN!$E$57:$E$150,B95) -> 0 | J95: =COUNTIF(DATA_SURAT_PELANTIKAN!$F$57:$F$150,B95) -> 0 | K95: =COUNTIF(DATA_SURAT_PELANTIKAN!$G$57:$G$150,B95) -> 0
A96: 92 | B96: Dr. Siti Amirah binti Ahmad Tarmizi | C96: =COUNTIF(DATA_SURAT_PELANTIKAN!$D$2:$D$56,B96) -> 0 | D96: =COUNTIF(DATA_SURAT_PELANTIKAN!$E$2:$E$56,B96) -> 0 | E96: =COUNTIF(DATA_SURAT_PELANTIKAN!$F$2:$F$56,B96) -> 0 | F96: =COUNTIF(DATA_SURAT_PELANTIKAN!$G$2:$G$56,B96) -> 0 | G96: =SUM(C96:F96) -> 0 | H96: =COUNTIF(DATA_SURAT_PELANTIKAN!$D$57:$D$150,B96) -> 0 | I96: =COUNTIF(DATA_SURAT_PELANTIKAN!$E$57:$E$150,B96) -> 0 | J96: =COUNTIF(DATA_SURAT_PELANTIKAN!$F$57:$F$150,B96) -> 0 | K96: =COUNTIF(DATA_SURAT_PELANTIKAN!$G$57:$G$150,B96) -> 0
A97: 93 | B97: Dr. Mohd Shahril Nizam bin Md Radzi | C97: =COUNTIF(DATA_SURAT_PELANTIKAN!$D$2:$D$56,B97) -> 0 | D97: =COUNTIF(DATA_SURAT_PELANTIKAN!$E$2:$E$56,B97) -> 0 | E97: =COUNTIF(DATA_SURAT_PELANTIKAN!$F$2:$F$56,B97) -> 0 | F97: =COUNTIF(DATA_SURAT_PELANTIKAN!$G$2:$G$56,B97) -> 0 | G97: =SUM(C97:F97) -> 0 | H97: =COUNTIF(DATA_SURAT_PELANTIKAN!$D$57:$D$150,B97) -> 0 | I97: =COUNTIF(DATA_SURAT_PELANTIKAN!$E$57:$E$150,B97) -> 0 | J97: =COUNTIF(DATA_SURAT_PELANTIKAN!$F$57:$F$150,B97) -> 0 | K97: =COUNTIF(DATA_SURAT_PELANTIKAN!$G$57:$G$150,B97) -> 0
A98: 94 | B98: Prof. Madya Dr. Mohd Zain bin Mubarak | C98: =COUNTIF(DATA_SURAT_PELANTIKAN!$D$2:$D$56,B98) -> 0 | D98: =COUNTIF(DATA_SURAT_PELANTIKAN!$E$2:$E$56,B98) -> 0 | E98: =COUNTIF(DATA_SURAT_PELANTIKAN!$F$2:$F$56,B98) -> 0 | F98: =COUNTIF(DATA_SURAT_PELANTIKAN!$G$2:$G$56,B98) -> 0 | G98: =SUM(C98:F98) -> 0 | H98: =COUNTIF(DATA_SURAT_PELANTIKAN!$D$57:$D$150,B98) -> 0 | I98: =COUNTIF(DATA_SURAT_PELANTIKAN!$E$57:$E$150,B98) -> 0 | J98: =COUNTIF(DATA_SURAT_PELANTIKAN!$F$57:$F$150,B98) -> 0 | K98: =COUNTIF(DATA_SURAT_PELANTIKAN!$G$57:$G$150,B98) -> 0
A99: 95 | B99: Dr. Yukhtamarani a/p Permarupan | C99: =COUNTIF(DATA_SURAT_PELANTIKAN!$D$2:$D$56,B99) -> 0 | D99: =COUNTIF(DATA_SURAT_PELANTIKAN!$E$2:$E$56,B99) -> 0 | E99: =COUNTIF(DATA_SURAT_PELANTIKAN!$F$2:$F$56,B99) -> 0 | F99: =COUNTIF(DATA_SURAT_PELANTIKAN!$G$2:$G$56,B99) -> 0 | G99: =SUM(C99:F99) -> 0 | H99: =COUNTIF(DATA_SURAT_PELANTIKAN!$D$57:$D$150,B99) -> 0 | I99: =COUNTIF(DATA_SURAT_PELANTIKAN!$E$57:$E$150,B99) -> 0 | J99: =COUNTIF(DATA_SURAT_PELANTIKAN!$F$57:$F$150,B99) -> 0 | K99: =COUNTIF(DATA_SURAT_PELANTIKAN!$G$57:$G$150,B99) -> 0
A100: 96 | B100: Prof. Dr. Naresh Kumar a/l Samy | C100: =COUNTIF(DATA_SURAT_PELANTIKAN!$D$2:$D$56,B100) -> 0 | D100: =COUNTIF(DATA_SURAT_PELANTIKAN!$E$2:$E$56,B100) -> 0 | E100: =COUNTIF(DATA_SURAT_PELANTIKAN!$F$2:$F$56,B100) -> 0 | F100: =COUNTIF(DATA_SURAT_PELANTIKAN!$G$2:$G$56,B100) -> 0 | G100: =SUM(C100:F100) -> 0 | H100: =COUNTIF(DATA_SURAT_PELANTIKAN!$D$57:$D$150,B100) -> 0 | I100: =COUNTIF(DATA_SURAT_PELANTIKAN!$E$57:$E$150,B100) -> 0 | J100: =COUNTIF(DATA_SURAT_PELANTIKAN!$F$57:$F$150,B100) -> 0 | K100: =COUNTIF(DATA_SURAT_PELANTIKAN!$G$57:$G$150,B100) -> 0
G101: =SUM(G5:G91) -> 213
